Workbook
Name Excel_BuiltIn_Print_Area: 'Cross Reference List'!#REF!
Name pricepercc: #REF!
Name pricepercc: #REF!
Name pricepercc: #REF!
Name pricepercc2: #REF!
Name pricepercyl: #REF!
Name pricepercyl: #REF!
Name pricepercyl: #REF!

Sheet TM-A0001-AA
A1: University | B1: McGill University | D1: Car # | E1: 99999 | G1: Asm Cost | H1: =E20+J30+I47+J59+I65 -> 0
A2: System | B2: Random Stuff | G2: Qty | H2: 1
A3: Assembly | B3: Push bar
A4: P/N Base | B4: A0001 | G4: Extended Cost | H4: =H1*H2 -> 0
A5: Suffix | B5: AA
A6: Details
A9: Parts
A10: P/N | B10: Part | C10: Part Cost | D10: Quantity | E10: Sub Total
E11: =C11*D11 -> 0
E12: =C12*D12 -> 0
E13: =C13*D13 -> 0
E14: =C14*D14 -> 0
E15: =C15*D15 -> 0
E16: =C16*D16 -> 0
E17: =C17*D17 -> 0
E18: =C18*D18 -> 0
E19: =C19*D19 -> 0
D20: Sub Total | E20: =SUM(E11:E19) -> 0
A22: Materials
A23: ID | B23: Material | C23: Use | D23: UnitCost | E23: Size1 | F23: Unit1 | G23: Size2 | H23: Unit2 | I23: Quantity | J23: Sub Total
B24: =IF($A24<>"",VLOOKUP($A24,tblMaterials2013!$A$3:$L$10000,2,FALSE),"") | D24: =IF($A24<>"",VLOOKUP($A24,tblMaterials2013!$A$3:$L$1000,5,FALSE),"") | F24: =IF($A24<>"",IF(VLOOKUP($A24,tblMaterials2013!$A$3:$L$10000,6,FALSE)<>FALSE,VLOOKUP($A24,tblMaterials2013!$A$3:$L$10000,6,FALSE),""), "") | H24: =IF($A24<>"",IF(VLOOKUP($A24,tblMaterials2013!$A$3:$L$10000,7,FALSE)<>FALSE,VLOOKUP($A24,tblMaterials2013!$A$3:$L$10000,7,FALSE),""), "") | J24: =IF($A24="",0,D24*I24) -> 0
B25: =IF($A25<>"",VLOOKUP($A25,tblMaterials2013!$A$3:$L$10000,2,FALSE),"") | D25: =IF($A25<>"",VLOOKUP($A25,tblMaterials2013!$A$3:$L$1000,5,FALSE),"") | F25: =IF($A25<>"",IF(VLOOKUP($A25,tblMaterials2013!$A$3:$L$10000,6,FALSE)<>FALSE,VLOOKUP($A25,tblMaterials2013!$A$3:$L$10000,6,FALSE),""), "") | H25: =IF($A25<>"",IF(VLOOKUP($A25,tblMaterials2013!$A$3:$L$10000,7,FALSE)<>FALSE,VLOOKUP($A25,tblMaterials2013!$A$3:$L$10000,7,FALSE),""), "") | J25: =IF($A25="",0,D25*I25) -> 0
B26: =IF($A26<>"",VLOOKUP($A26,tblMaterials2013!$A$3:$L$10000,2,FALSE),"") | D26: =IF($A26<>"",VLOOKUP($A26,tblMaterials2013!$A$3:$L$1000,5,FALSE),"") | F26: =IF($A26<>"",IF(VLOOKUP($A26,tblMaterials2013!$A$3:$L$10000,6,FALSE)<>FALSE,VLOOKUP($A26,tblMaterials2013!$A$3:$L$10000,6,FALSE),""), "") | H26: =IF($A26<>"",IF(VLOOKUP($A26,tblMaterials2013!$A$3:$L$10000,7,FALSE)<>FALSE,VLOOKUP($A26,tblMaterials2013!$A$3:$L$10000,7,FALSE),""), "") | J26: =IF($A26="",0,D26*I26) -> 0
B27: =IF($A27<>"",VLOOKUP($A27,tblMaterials2013!$A$3:$L$10000,2,FALSE),"") | D27: =IF($A27<>"",VLOOKUP($A27,tblMaterials2013!$A$3:$L$1000,5,FALSE),"") | F27: =IF($A27<>"",IF(VLOOKUP($A27,tblMaterials2013!$A$3:$L$10000,6,FALSE)<>FALSE,VLOOKUP($A27,tblMaterials2013!$A$3:$L$10000,6,FALSE),""), "") | H27: =IF($A27<>"",IF(VLOOKUP($A27,tblMaterials2013!$A$3:$L$10000,7,FALSE)<>FALSE,VLOOKUP($A27,tblMaterials2013!$A$3:$L$10000,7,FALSE),""), "") | J27: =IF($A27="",0,D27*I27) -> 0
B28: =IF($A28<>"",VLOOKUP($A28,tblMaterials2013!$A$3:$L$10000,2,FALSE),"") | D28: =IF($A28<>"",VLOOKUP($A28,tblMaterials2013!$A$3:$L$1000,5,FALSE),"") | F28: =IF($A28<>"",IF(VLOOKUP($A28,tblMaterials2013!$A$3:$L$10000,6,FALSE)<>FALSE,VLOOKUP($A28,tblMaterials2013!$A$3:$L$10000,6,FALSE),""), "") | H28: =IF($A28<>"",IF(VLOOKUP($A28,tblMaterials2013!$A$3:$L$10000,7,FALSE)<>FALSE,VLOOKUP($A28,tblMaterials2013!$A$3:$L$10000,7,FALSE),""), "") | J28: =IF($A28="",0,D28*I28) -> 0
B29: =IF($A29<>"",VLOOKUP($A29,tblMaterials2013!$A$3:$L$10000,2,FALSE),"") | D29: =IF($A29<>"",VLOOKUP($A29,tblMaterials2013!$A$3:$L$1000,5,FALSE),"") | F29: =IF($A29<>"",IF(VLOOKUP($A29,tblMaterials2013!$A$3:$L$10000,6,FALSE)<>FALSE,VLOOKUP($A29,tblMaterials2013!$A$3:$L$10000,6,FALSE),""), "") | H29: =IF($A29<>"",IF(VLOOKUP($A29,tblMaterials2013!$A$3:$L$10000,7,FALSE)<>FALSE,VLOOKUP($A29,tblMaterials2013!$A$3:$L$10000,7,FALSE),""), "") | J29: =IF($A29="",0,D29*I29) -> 0
I30: Sub Total | J30: =SUM(J24:J29) -> 0
A32: Processes
A33: ID | B33: Process | C33: Use | D33: UnitCost | E33: Unit | F33: Quantity | G33: Multiplier ID | H33: Mult. Val. | I33: Sub Total
B34: =IF($A34<>"",VLOOKUP($A34,tblProcesses2013!$A$3:$J$9998,2,FALSE),"") | D34: =IF($A34<>"",VLOOKUP($A34,tblProcesses2013!$A$3:$J$9998,3,FALSE),"") | E34: =IF($A34<>"",VLOOKUP($A34,tblProcesses2013!$A$3:$J$9998,4,FALSE),"") | G34: =IF($A34<>"",IF(ISBLANK(VLOOKUP($A34,tblProcesses2013!$A$3:$J$9998,8,FALSE)),"","?"),"") | H34: =IF(AND($G34<>"",$G34<>"?"),VLOOKUP($G34,tblProcessMultipliers2013!$A$3:$E$10000,3,FALSE),"") | I34: =IF($A34<>"",IF($H34<>"",$D34*$F34*$H34,$D34*$F34),0) -> 0
B35: =IF($A35<>"",VLOOKUP($A35,tblProcesses2013!$A$3:$J$9998,2,FALSE),"") | D35: =IF($A35<>"",VLOOKUP($A35,tblProcesses2013!$A$3:$J$9998,3,FALSE),"") | E35: =IF($A35<>"",VLOOKUP($A35,tblProcesses2013!$A$3:$J$9998,4,FALSE),"") | G35: =IF($A35<>"",IF(ISBLANK(VLOOKUP($A35,tblProcesses2013!$A$3:$J$9998,8,FALSE)),"","?"),"") | H35: =IF(AND($G35<>"",$G35<>"?"),VLOOKUP($G35,tblProcessMultipliers2013!$A$3:$E$10000,3,FALSE),"") | I35: =IF($A35<>"",IF($H35<>"",$D35*$F35*$H35,$D35*$F35),0) -> 0
B36: =IF($A36<>"",VLOOKUP($A36,tblProcesses2013!$A$3:$J$9998,2,FALSE),"") | D36: =IF($A36<>"",VLOOKUP($A36,tblProcesses2013!$A$3:$J$9998,3,FALSE),"") | E36: =IF($A36<>"",VLOOKUP($A36,tblProcesses2013!$A$3:$J$9998,4,FALSE),"") | G36: =IF($A36<>"",IF(ISBLANK(VLOOKUP($A36,tblProcesses2013!$A$3:$J$9998,8,FALSE)),"","?"),"") | H36: =IF(AND($G36<>"",$G36<>"?"),VLOOKUP($G36,tblProcessMultipliers2013!$A$3:$E$10000,3,FALSE),"") | I36: =IF($A36<>"",IF($H36<>"",$D36*$F36*$H36,$D36*$F36),0) -> 0
B37: =IF($A37<>"",VLOOKUP($A37,tblProcesses2013!$A$3:$J$9998,2,FALSE),"") | D37: =IF($A37<>"",VLOOKUP($A37,tblProcesses2013!$A$3:$J$9998,3,FALSE),"") | E37: =IF($A37<>"",VLOOKUP($A37,tblProcesses2013!$A$3:$J$9998,4,FALSE),"") | G37: =IF($A37<>"",IF(ISBLANK(VLOOKUP($A37,tblProcesses2013!$A$3:$J$9998,8,FALSE)),"","?"),"") | H37: =IF(AND($G37<>"",$G37<>"?"),VLOOKUP($G37,tblProcessMultipliers2013!$A$3:$E$10000,3,FALSE),"") | I37: =IF($A37<>"",IF($H37<>"",$D37*$F37*$H37,$D37*$F37),0) -> 0
B38: =IF($A38<>"",VLOOKUP($A38,tblProcesses2013!$A$3:$J$9998,2,FALSE),"") | D38: =IF($A38<>"",VLOOKUP($A38,tblProcesses2013!$A$3:$J$9998,3,FALSE),"") | E38: =IF($A38<>"",VLOOKUP($A38,tblProcesses2013!$A$3:$J$9998,4,FALSE),"") | G38: =IF($A38<>"",IF(ISBLANK(VLOOKUP($A38,tblProcesses2013!$A$3:$J$9998,8,FALSE)),"","?"),"") | H38: =IF(AND($G38<>"",$G38<>"?"),VLOOKUP($G38,tblProcessMultipliers2013!$A$3:$E$10000,3,FALSE),"") | I38: =IF($A38<>"",IF($H38<>"",$D38*$F38*$H38,$D38*$F38),0) -> 0
B39: =IF($A39<>"",VLOOKUP($A39,tblProcesses2013!$A$3:$J$9998,2,FALSE),"") | D39: =IF($A39<>"",VLOOKUP($A39,tblProcesses2013!$A$3:$J$9998,3,FALSE),"") | E39: =IF($A39<>"",VLOOKUP($A39,tblProcesses2013!$A$3:$J$9998,4,FALSE),"") | G39: =IF($A39<>"",IF(ISBLANK(VLOOKUP($A39,tblProcesses2013!$A$3:$J$9998,8,FALSE)),"","?"),"") | H39: =IF(AND($G39<>"",$G39<>"?"),VLOOKUP($G39,tblProcessMultipliers2013!$A$3:$E$10000,3,FALSE),"") | I39: =IF($A39<>"",IF($H39<>"",$D39*$F39*$H39,$D39*$F39),0) -> 0
B40: =IF($A40<>"",VLOOKUP($A40,tblProcesses2013!$A$3:$J$9998,2,FALSE),"") | D40: =IF($A40<>"",VLOOKUP($A40,tblProcesses2013!$A$3:$J$9998,3,FALSE),"") | E40: =IF($A40<>"",VLOOKUP($A40,tblProcesses2013!$A$3:$J$9998,4,FALSE),"") | G40: =IF($A40<>"",IF(ISBLANK(VLOOKUP($A40,tblProcesses2013!$A$3:$J$9998,8,FALSE)),"","?"),"") | H40: =IF(AND($G40<>"",$G40<>"?"),VLOOKUP($G40,tblProcessMultipliers2013!$A$3:$E$10000,3,FALSE),"") | I40: =IF($A40<>"",IF($H40<>"",$D40*$F40*$H40,$D40*$F40),0) -> 0
B41: =IF($A41<>"",VLOOKUP($A41,tblProcesses2013!$A$3:$J$9998,2,FALSE),"") | D41: =IF($A41<>"",VLOOKUP($A41,tblProcesses2013!$A$3:$J$9998,3,FALSE),"") | E41: =IF($A41<>"",VLOOKUP($A41,tblProcesses2013!$A$3:$J$9998,4,FALSE),"") | G41: =IF($A41<>"",IF(ISBLANK(VLOOKUP($A41,tblProcesses2013!$A$3:$J$9998,8,FALSE)),"","?"),"") | H41: =IF(AND($G41<>"",$G41<>"?"),VLOOKUP($G41,tblProcessMultipliers2013!$A$3:$E$10000,3,FALSE),"") | I41: =IF($A41<>"",IF($H41<>"",$D41*$F41*$H41,$D41*$F41),0) -> 0
B42: =IF($A42<>"",VLOOKUP($A42,tblProcesses2013!$A$3:$J$9998,2,FALSE),"") | D42: =IF($A42<>"",VLOOKUP($A42,tblProcesses2013!$A$3:$J$9998,3,FALSE),"") | E42: =IF($A42<>"",VLOOKUP($A42,tblProcesses2013!$A$3:$J$9998,4,FALSE),"") | G42: =IF($A42<>"",IF(ISBLANK(VLOOKUP($A42,tblProcesses2013!$A$3:$J$9998,8,FALSE)),"","?"),"") | H42: =IF(AND($G42<>"",$G42<>"?"),VLOOKUP($G42,tblProcessMultipliers2013!$A$3:$E$10000,3,FALSE),"") | I42: =IF($A42<>"",IF($H42<>"",$D42*$F42*$H42,$D42*$F42),0) -> 0
B43: =IF($A43<>"",VLOOKUP($A43,tblProcesses2013!$A$3:$J$9998,2,FALSE),"") | D43: =IF($A43<>"",VLOOKUP($A43,tblProcesses2013!$A$3:$J$9998,3,FALSE),"") | E43: =IF($A43<>"",VLOOKUP($A43,tblProcesses2013!$A$3:$J$9998,4,FALSE),"") | G43: =IF($A43<>"",IF(ISBLANK(VLOOKUP($A43,tblProcesses2013!$A$3:$J$9998,8,FALSE)),"","?"),"") | H43: =IF(AND($G43<>"",$G43<>"?"),VLOOKUP($G43,tblProcessMultipliers2013!$A$3:$E$10000,3,FALSE),"") | I43: =IF($A43<>"",IF($H43<>"",$D43*$F43*$H43,$D43*$F43),0) -> 0
B44: =IF($A44<>"",VLOOKUP($A44,tblProcesses2013!$A$3:$J$9998,2,FALSE),"") | D44: =IF($A44<>"",VLOOKUP($A44,tblProcesses2013!$A$3:$J$9998,3,FALSE),"") | E44: =IF($A44<>"",VLOOKUP($A44,tblProcesses2013!$A$3:$J$9998,4,FALSE),"") | G44: =IF($A44<>"",IF(ISBLANK(VLOOKUP($A44,tblProcesses2013!$A$3:$J$9998,8,FALSE)),"","?"),"") | H44: =IF(AND($G44<>"",$G44<>"?"),VLOOKUP($G44,tblProcessMultipliers2013!$A$3:$E$10000,3,FALSE),"") | I44: =IF($A44<>"",IF($H44<>"",$D44*$F44*$H44,$D44*$F44),0) -> 0
B45: =IF($A45<>"",VLOOKUP($A45,tblProcesses2013!$A$3:$J$9998,2,FALSE),"") | D45: =IF($A45<>"",VLOOKUP($A45,tblProcesses2013!$A$3:$J$9998,3,FALSE),"") | E45: =IF($A45<>"",VLOOKUP($A45,tblProcesses2013!$A$3:$J$9998,4,FALSE),"") | G45: =IF($A45<>"",IF(ISBLANK(VLOOKUP($A45,tblProcesses2013!$A$3:$J$9998,8,FALSE)),"","?"),"") | H45: =IF(AND($G45<>"",$G45<>"?"),VLOOKUP($G45,tblProcessMultipliers2013!$A$3:$E$10000,3,FALSE),"") | I45: =IF($A45<>"",IF($H45<>"",$D45*$F45*$H45,$D45*$F45),0) -> 0
B46: =IF($A46<>"",VLOOKUP($A46,tblProcesses2013!$A$3:$J$9998,2,FALSE),"") | D46: =IF($A46<>"",VLOOKUP($A46,tblProcesses2013!$A$3:$J$9998,3,FALSE),"") | E46: =IF($A46<>"",VLOOKUP($A46,tblProcesses2013!$A$3:$J$9998,4,FALSE),"") | G46: =IF($A46<>"",IF(ISBLANK(VLOOKUP($A46,tblProcesses2013!$A$3:$J$9998,8,FALSE)),"","?"),"") | H46: =IF(AND($G46<>"",$G46<>"?"),VLOOKUP($G46,tblProcessMultipliers2013!$A$3:$E$10000,3,FALSE),"") | I46: =IF($A46<>"",IF($H46<>"",$D46*$F46*$H46,$D46*$F46),0) -> 0
H47: Sub Total | I47: =SUM(I34:I46) -> 0
A49: Fasteners
A50: ID | B50: Fastener | C50: Use | D50: UnitCost | E50: Size1 | F50: Unit1 | G50: Size2 | H50: Unit2 | I50: Quantity | J50: Sub Total
B51: =IF($A51<>"",VLOOKUP($A51,tblFasteners2013!$A$4:$R$9999,2,FALSE),"") | D51: =IF($A51<>"",VLOOKUP($A51,tblFasteners2013!$A$4:$R$9999,11,FALSE),"") | F51: =IF($A51<>"",IF(VLOOKUP($A51,tblFasteners2013!$A$4:$R$9999,4,FALSE)<>FALSE,VLOOKUP($A51,tblFasteners2013!$A$4:$R$9999,4,FALSE),""),"") | H51: =IF($A51<>"",IF(VLOOKUP($A51,tblFasteners2013!$A$4:$R$9999,6,FALSE)<>FALSE,VLOOKUP($A51,tblFasteners2013!$A$4:$R$9999,6,FALSE),""),"") | J51: =IF($A51<>"",D51*I51,0) -> 0
B52: =IF($A52<>"",VLOOKUP($A52,tblFasteners2013!$A$4:$R$9999,2,FALSE),"") | D52: =IF($A52<>"",VLOOKUP($A52,tblFasteners2013!$A$4:$R$9999,11,FALSE),"") | F52: =IF($A52<>"",IF(VLOOKUP($A52,tblFasteners2013!$A$4:$R$9999,4,FALSE)<>FALSE,VLOOKUP($A52,tblFasteners2013!$A$4:$R$9999,4,FALSE),""),"") | H52: =IF($A52<>"",IF(VLOOKUP($A52,tblFasteners2013!$A$4:$R$9999,6,FALSE)<>FALSE,VLOOKUP($A52,tblFasteners2013!$A$4:$R$9999,6,FALSE),""),"") | J52: =IF($A52<>"",D52*I52,0) -> 0
B53: =IF($A53<>"",VLOOKUP($A53,tblFasteners2013!$A$4:$R$9999,2,FALSE),"") | D53: =IF($A53<>"",VLOOKUP($A53,tblFasteners2013!$A$4:$R$9999,11,FALSE),"") | F53: =IF($A53<>"",IF(VLOOKUP($A53,tblFasteners2013!$A$4:$R$9999,4,FALSE)<>FALSE,VLOOKUP($A53,tblFasteners2013!$A$4:$R$9999,4,FALSE),""),"") | H53: =IF($A53<>"",IF(VLOOKUP($A53,tblFasteners2013!$A$4:$R$9999,6,FALSE)<>FALSE,VLOOKUP($A53,tblFasteners2013!$A$4:$R$9999,6,FALSE),""),"") | J53: =IF($A53<>"",D53*I53,0) -> 0
B54: =IF($A54<>"",VLOOKUP($A54,tblFasteners2013!$A$4:$R$9999,2,FALSE),"") | D54: =IF($A54<>"",VLOOKUP($A54,tblFasteners2013!$A$4:$R$9999,11,FALSE),"") | F54: =IF($A54<>"",IF(VLOOKUP($A54,tblFasteners2013!$A$4:$R$9999,4,FALSE)<>FALSE,VLOOKUP($A54,tblFasteners2013!$A$4:$R$9999,4,FALSE),""),"") | H54: =IF($A54<>"",IF(VLOOKUP($A54,tblFasteners2013!$A$4:$R$9999,6,FALSE)<>FALSE,VLOOKUP($A54,tblFasteners2013!$A$4:$R$9999,6,FALSE),""),"") | J54: =IF($A54<>"",D54*I54,0) -> 0
B55: =IF($A55<>"",VLOOKUP($A55,tblFasteners2013!$A$4:$R$9999,2,FALSE),"") | D55: =IF($A55<>"",VLOOKUP($A55,tblFasteners2013!$A$4:$R$9999,11,FALSE),"") | F55: =IF($A55<>"",IF(VLOOKUP($A55,tblFasteners2013!$A$4:$R$9999,4,FALSE)<>FALSE,VLOOKUP($A55,tblFasteners2013!$A$4:$R$9999,4,FALSE),""),"") | H55: =IF($A55<>"",IF(VLOOKUP($A55,tblFasteners2013!$A$4:$R$9999,6,FALSE)<>FALSE,VLOOKUP($A55,tblFasteners2013!$A$4:$R$9999,6,FALSE),""),"") | J55: =IF($A55<>"",D55*I55,0) -> 0
B56: =IF($A56<>"",VLOOKUP($A56,tblFasteners2013!$A$4:$R$9999,2,FALSE),"") | D56: =IF($A56<>"",VLOOKUP($A56,tblFasteners2013!$A$4:$R$9999,11,FALSE),"") | F56: =IF($A56<>"",IF(VLOOKUP($A56,tblFasteners2013!$A$4:$R$9999,4,FALSE)<>FALSE,VLOOKUP($A56,tblFasteners2013!$A$4:$R$9999,4,FALSE),""),"") | H56: =IF($A56<>"",IF(VLOOKUP($A56,tblFasteners2013!$A$4:$R$9999,6,FALSE)<>FALSE,VLOOKUP($A56,tblFasteners2013!$A$4:$R$9999,6,FALSE),""),"") | J56: =IF($A56<>"",D56*I56,0) -> 0
B57: =IF($A57<>"",VLOOKUP($A57,tblFasteners2013!$A$4:$R$9999,2,FALSE),"") | D57: =IF($A57<>"",VLOOKUP($A57,tblFasteners2013!$A$4:$R$9999,11,FALSE),"") | F57: =IF($A57<>"",IF(VLOOKUP($A57,tblFasteners2013!$A$4:$R$9999,4,FALSE)<>FALSE,VLOOKUP($A57,tblFasteners2013!$A$4:$R$9999,4,FALSE),""),"") | H57: =IF($A57<>"",IF(VLOOKUP($A57,tblFasteners2013!$A$4:$R$9999,6,FALSE)<>FALSE,VLOOKUP($A57,tblFasteners2013!$A$4:$R$9999,6,FALSE),""),"") | J57: =IF($A57<>"",D57*I57,0) -> 0
B58: =IF($A58<>"",VLOOKUP($A58,tblFasteners2013!$A$4:$R$9999,2,FALSE),"") | D58: =IF($A58<>"",VLOOKUP($A58,tblFasteners2013!$A$4:$R$9999,11,FALSE),"") | F58: =IF($A58<>"",IF(VLOOKUP($A58,tblFasteners2013!$A$4:$R$9999,4,FALSE)<>FALSE,VLOOKUP($A58,tblFasteners2013!$A$4:$R$9999,4,FALSE),""),"") | H58: =IF($A58<>"",IF(VLOOKUP($A58,tblFasteners2013!$A$4:$R$9999,6,FALSE)<>FALSE,VLOOKUP($A58,tblFasteners2013!$A$4:$R$9999,6,FALSE),""),"") | J58: =IF($A58<>"",D58*I58,0) -> 0
I59: Sub Total | J59: =SUM(J51:J58) -> 0
A61: Tooling
A62: ID | B62: Tooling | C62: Use | D62: UnitCost | E62: Unit | F62: Quantity | G62: PVF | H62: FracIncld | I62: Sub Total
B63: =IF($A63<>"",VLOOKUP($A63,tblToolings2013!$A$3:$F$10000,3,FALSE),"") | D63: =IF($A63<>"",VLOOKUP($A63,tblToolings2013!$A$3:$F$10000,4,FALSE),"") | E63: =IF($A63<>"",VLOOKUP($A63,tblToolings2013!$A$3:$F$10000,5,FALSE),"") | G63: 3000 | I63: =IF($A63<>"",D63*F63/G63,0) -> 0
B64: =IF($A64<>"",VLOOKUP($A64,tblToolings2013!$A$3:$F$10000,3,FALSE),"") | D64: =IF($A64<>"",VLOOKUP($A64,tblToolings2013!$A$3:$F$10000,4,FALSE),"") | E64: =IF($A64<>"",VLOOKUP($A64,tblToolings2013!$A$3:$F$10000,5,FALSE),"") | G64: 3000 | I64: =IF($A64<>"",D64*F64/G64,0) -> 0
H65: Sub Total | I65: =SUM(I63:I64) -> 0

Sheet TM-00001-AA
A1: University | B1: McGill University | D1: Car # | E1: 99999 | G1: Asm Cost | H1: =J18+I35+J47+I53 -> 0
A2: System | B2: Random Stuff | G2: Qty | H2: 1
A3: Assembly | B3: Push bar
A4: Part | B4: Cup holder
A5: P/N Base | B5: 00001 | G5: Extended Cost | H5: =H1*H2 -> 0
A6: Suffix | B6: AA
A7: Details
A10: Materials
A11: ID | B11: Material | C11: Use | D11: UnitCost | E11: Size1 | F11: Unit1 | G11: Size2 | H11: Unit2 | I11: Quantity | J11: Sub Total
B12: =IF($A12<>"",VLOOKUP($A12,tblMaterials2013!$A$3:$L$10000,2,FALSE),"") | D12: =IF($A12<>"",VLOOKUP($A12,tblMaterials2013!$A$3:$L$1000,5,FALSE),"") | F12: =IF($A12<>"",IF(VLOOKUP($A12,tblMaterials2013!$A$3:$L$10000,6,FALSE)<>FALSE,VLOOKUP($A12,tblMaterials2013!$A$3:$L$10000,6,FALSE),""), "") | H12: =IF($A12<>"",IF(VLOOKUP($A12,tblMaterials2013!$A$3:$L$10000,7,FALSE)<>FALSE,VLOOKUP($A12,tblMaterials2013!$A$3:$L$10000,7,FALSE),""), "") | J12: =IF($A12="",0,D12*I12) -> 0
B13: =IF($A13<>"",VLOOKUP($A13,tblMaterials2013!$A$3:$L$10000,2,FALSE),"") | D13: =IF($A13<>"",VLOOKUP($A13,tblMaterials2013!$A$3:$L$1000,5,FALSE),"") | F13: =IF($A13<>"",IF(VLOOKUP($A13,tblMaterials2013!$A$3:$L$10000,6,FALSE)<>FALSE,VLOOKUP($A13,tblMaterials2013!$A$3:$L$10000,6,FALSE),""), "") | H13: =IF($A13<>"",IF(VLOOKUP($A13,tblMaterials2013!$A$3:$L$10000,7,FALSE)<>FALSE,VLOOKUP($A13,tblMaterials2013!$A$3:$L$10000,7,FALSE),""), "") | J13: =IF($A13="",0,D13*I13) -> 0
B14: =IF($A14<>"",VLOOKUP($A14,tblMaterials2013!$A$3:$L$10000,2,FALSE),"") | D14: =IF($A14<>"",VLOOKUP($A14,tblMaterials2013!$A$3:$L$1000,5,FALSE),"") | F14: =IF($A14<>"",IF(VLOOKUP($A14,tblMaterials2013!$A$3:$L$10000,6,FALSE)<>FALSE,VLOOKUP($A14,tblMaterials2013!$A$3:$L$10000,6,FALSE),""), "") | H14: =IF($A14<>"",IF(VLOOKUP($A14,tblMaterials2013!$A$3:$L$10000,7,FALSE)<>FALSE,VLOOKUP($A14,tblMaterials2013!$A$3:$L$10000,7,FALSE),""), "") | J14: =IF($A14="",0,D14*I14) -> 0
B15: =IF($A15<>"",VLOOKUP($A15,tblMaterials2013!$A$3:$L$10000,2,FALSE),"") | D15: =IF($A15<>"",VLOOKUP($A15,tblMaterials2013!$A$3:$L$1000,5,FALSE),"") | F15: =IF($A15<>"",IF(VLOOKUP($A15,tblMaterials2013!$A$3:$L$10000,6,FALSE)<>FALSE,VLOOKUP($A15,tblMaterials2013!$A$3:$L$10000,6,FALSE),""), "") | H15: =IF($A15<>"",IF(VLOOKUP($A15,tblMaterials2013!$A$3:$L$10000,7,FALSE)<>FALSE,VLOOKUP($A15,tblMaterials2013!$A$3:$L$10000,7,FALSE),""), "") | J15: =IF($A15="",0,D15*I15) -> 0
B16: =IF($A16<>"",VLOOKUP($A16,tblMaterials2013!$A$3:$L$10000,2,FALSE),"") | D16: =IF($A16<>"",VLOOKUP($A16,tblMaterials2013!$A$3:$L$1000,5,FALSE),"") | F16: =IF($A16<>"",IF(VLOOKUP($A16,tblMaterials2013!$A$3:$L$10000,6,FALSE)<>FALSE,VLOOKUP($A16,tblMaterials2013!$A$3:$L$10000,6,FALSE),""), "") | H16: =IF($A16<>"",IF(VLOOKUP($A16,tblMaterials2013!$A$3:$L$10000,7,FALSE)<>FALSE,VLOOKUP($A16,tblMaterials2013!$A$3:$L$10000,7,FALSE),""), "") | J16: =IF($A16="",0,D16*I16) -> 0
B17: =IF($A17<>"",VLOOKUP($A17,tblMaterials2013!$A$3:$L$10000,2,FALSE),"") | D17: =IF($A17<>"",VLOOKUP($A17,tblMaterials2013!$A$3:$L$1000,5,FALSE),"") | F17: =IF($A17<>"",IF(VLOOKUP($A17,tblMaterials2013!$A$3:$L$10000,6,FALSE)<>FALSE,VLOOKUP($A17,tblMaterials2013!$A$3:$L$10000,6,FALSE),""), "") | H17: =IF($A17<>"",IF(VLOOKUP($A17,tblMaterials2013!$A$3:$L$10000,7,FALSE)<>FALSE,VLOOKUP($A17,tblMaterials2013!$A$3:$L$10000,7,FALSE),""), "") | J17: =IF($A17="",0,D17*I17) -> 0
I18: Sub Total | J18: =SUM(J12:J17) -> 0
A20: Processes
A21: ID | B21: Process | C21: Use | D21: UnitCost | E21: Unit | F21: Quantity | G21: Multiplier ID | H21: Mult. Val. | I21: Sub Total
B22: =IF($A22<>"",VLOOKUP($A22,tblProcesses2013!$A$3:$J$9998,2,FALSE),"") | D22: =IF($A22<>"",VLOOKUP($A22,tblProcesses2013!$A$3:$J$9998,3,FALSE),"") | E22: =IF($A22<>"",VLOOKUP($A22,tblProcesses2013!$A$3:$J$9998,4,FALSE),"") | G22: =IF($A22<>"",IF(ISBLANK(VLOOKUP($A22,tblProcesses2013!$A$3:$J$9998,8,FALSE)),"","?"),"") | H22: =IF(AND($G22<>"",$G22<>"?"),VLOOKUP($G22,tblProcessMultipliers2013!$A$3:$E$10000,3,FALSE),"") | I22: =IF($A22<>"",IF($H22<>"",$D22*$F22*$H22,$D22*$F22),0) -> 0
B23: =IF($A23<>"",VLOOKUP($A23,tblProcesses2013!$A$3:$J$9998,2,FALSE),"") | D23: =IF($A23<>"",VLOOKUP($A23,tblProcesses2013!$A$3:$J$9998,3,FALSE),"") | E23: =IF($A23<>"",VLOOKUP($A23,tblProcesses2013!$A$3:$J$9998,4,FALSE),"") | G23: =IF($A23<>"",IF(ISBLANK(VLOOKUP($A23,tblProcesses2013!$A$3:$J$9998,8,FALSE)),"","?"),"") | H23: =IF(AND($G23<>"",$G23<>"?"),VLOOKUP($G23,tblProcessMultipliers2013!$A$3:$E$10000,3,FALSE),"") | I23: =IF($A23<>"",IF($H23<>"",$D23*$F23*$H23,$D23*$F23),0) -> 0
B24: =IF($A24<>"",VLOOKUP($A24,tblProcesses2013!$A$3:$J$9998,2,FALSE),"") | D24: =IF($A24<>"",VLOOKUP($A24,tblProcesses2013!$A$3:$J$9998,3,FALSE),"") | E24: =IF($A24<>"",VLOOKUP($A24,tblProcesses2013!$A$3:$J$9998,4,FALSE),"") | G24: =IF($A24<>"",IF(ISBLANK(VLOOKUP($A24,tblProcesses2013!$A$3:$J$9998,8,FALSE)),"","?"),"") | H24: =IF(AND($G24<>"",$G24<>"?"),VLOOKUP($G24,tblProcessMultipliers2013!$A$3:$E$10000,3,FALSE),"") | I24: =IF($A24<>"",IF($H24<>"",$D24*$F24*$H24,$D24*$F24),0) -> 0
B25: =IF($A25<>"",VLOOKUP($A25,tblProcesses2013!$A$3:$J$9998,2,FALSE),"") | D25: =IF($A25<>"",VLOOKUP($A25,tblProcesses2013!$A$3:$J$9998,3,FALSE),"") | E25: =IF($A25<>"",VLOOKUP($A25,tblProcesses2013!$A$3:$J$9998,4,FALSE),"") | G25: =IF($A25<>"",IF(ISBLANK(VLOOKUP($A25,tblProcesses2013!$A$3:$J$9998,8,FALSE)),"","?"),"") | H25: =IF(AND($G25<>"",$G25<>"?"),VLOOKUP($G25,tblProcessMultipliers2013!$A$3:$E$10000,3,FALSE),"") | I25: =IF($A25<>"",IF($H25<>"",$D25*$F25*$H25,$D25*$F25),0) -> 0
B26: =IF($A26<>"",VLOOKUP($A26,tblProcesses2013!$A$3:$J$9998,2,FALSE),"") | D26: =IF($A26<>"",VLOOKUP($A26,tblProcesses2013!$A$3:$J$9998,3,FALSE),"") | E26: =IF($A26<>"",VLOOKUP($A26,tblProcesses2013!$A$3:$J$9998,4,FALSE),"") | G26: =IF($A26<>"",IF(ISBLANK(VLOOKUP($A26,tblProcesses2013!$A$3:$J$9998,8,FALSE)),"","?"),"") | H26: =IF(AND($G26<>"",$G26<>"?"),VLOOKUP($G26,tblProcessMultipliers2013!$A$3:$E$10000,3,FALSE),"") | I26: =IF($A26<>"",IF($H26<>"",$D26*$F26*$H26,$D26*$F26),0) -> 0
B27: =IF($A27<>"",VLOOKUP($A27,tblProcesses2013!$A$3:$J$9998,2,FALSE),"") | D27: =IF($A27<>"",VLOOKUP($A27,tblProcesses2013!$A$3:$J$9998,3,FALSE),"") | E27: =IF($A27<>"",VLOOKUP($A27,tblProcesses2013!$A$3:$J$9998,4,FALSE),"") | G27: =IF($A27<>"",IF(ISBLANK(VLOOKUP($A27,tblProcesses2013!$A$3:$J$9998,8,FALSE)),"","?"),"") | H27: =IF(AND($G27<>"",$G27<>"?"),VLOOKUP($G27,tblProcessMultipliers2013!$A$3:$E$10000,3,FALSE),"") | I27: =IF($A27<>"",IF($H27<>"",$D27*$F27*$H27,$D27*$F27),0) -> 0
B28: =IF($A28<>"",VLOOKUP($A28,tblProcesses2013!$A$3:$J$9998,2,FALSE),"") | D28: =IF($A28<>"",VLOOKUP($A28,tblProcesses2013!$A$3:$J$9998,3,FALSE),"") | E28: =IF($A28<>"",VLOOKUP($A28,tblProcesses2013!$A$3:$J$9998,4,FALSE),"") | G28: =IF($A28<>"",IF(ISBLANK(VLOOKUP($A28,tblProcesses2013!$A$3:$J$9998,8,FALSE)),"","?"),"") | H28: =IF(AND($G28<>"",$G28<>"?"),VLOOKUP($G28,tblProcessMultipliers2013!$A$3:$E$10000,3,FALSE),"") | I28: =IF($A28<>"",IF($H28<>"",$D28*$F28*$H28,$D28*$F28),0) -> 0
B29: =IF($A29<>"",VLOOKUP($A29,tblProcesses2013!$A$3:$J$9998,2,FALSE),"") | D29: =IF($A29<>"",VLOOKUP($A29,tblProcesses2013!$A$3:$J$9998,3,FALSE),"") | E29: =IF($A29<>"",VLOOKUP($A29,tblProcesses2013!$A$3:$J$9998,4,FALSE),"") | G29: =IF($A29<>"",IF(ISBLANK(VLOOKUP($A29,tblProcesses2013!$A$3:$J$9998,8,FALSE)),"","?"),"") | H29: =IF(AND($G29<>"",$G29<>"?"),VLOOKUP($G29,tblProcessMultipliers2013!$A$3:$E$10000,3,FALSE),"") | I29: =IF($A29<>"",IF($H29<>"",$D29*$F29*$H29,$D29*$F29),0) -> 0
B30: =IF($A30<>"",VLOOKUP($A30,tblProcesses2013!$A$3:$J$9998,2,FALSE),"") | D30: =IF($A30<>"",VLOOKUP($A30,tblProcesses2013!$A$3:$J$9998,3,FALSE),"") | E30: =IF($A30<>"",VLOOKUP($A30,tblProcesses2013!$A$3:$J$9998,4,FALSE),"") | G30: =IF($A30<>"",IF(ISBLANK(VLOOKUP($A30,tblProcesses2013!$A$3:$J$9998,8,FALSE)),"","?"),"") | H30: =IF(AND($G30<>"",$G30<>"?"),VLOOKUP($G30,tblProcessMultipliers2013!$A$3:$E$10000,3,FALSE),"") | I30: =IF($A30<>"",IF($H30<>"",$D30*$F30*$H30,$D30*$F30),0) -> 0
B31: =IF($A31<>"",VLOOKUP($A31,tblProcesses2013!$A$3:$J$9998,2,FALSE),"") | D31: =IF($A31<>"",VLOOKUP($A31,tblProcesses2013!$A$3:$J$9998,3,FALSE),"") | E31: =IF($A31<>"",VLOOKUP($A31,tblProcesses2013!$A$3:$J$9998,4,FALSE),"") | G31: =IF($A31<>"",IF(ISBLANK(VLOOKUP($A31,tblProcesses2013!$A$3:$J$9998,8,FALSE)),"","?"),"") | H31: =IF(AND($G31<>"",$G31<>"?"),VLOOKUP($G31,tblProcessMultipliers2013!$A$3:$E$10000,3,FALSE),"") | I31: =IF($A31<>"",IF($H31<>"",$D31*$F31*$H31,$D31*$F31),0) -> 0
B32: =IF($A32<>"",VLOOKUP($A32,tblProcesses2013!$A$3:$J$9998,2,FALSE),"") | D32: =IF($A32<>"",VLOOKUP($A32,tblProcesses2013!$A$3:$J$9998,3,FALSE),"") | E32: =IF($A32<>"",VLOOKUP($A32,tblProcesses2013!$A$3:$J$9998,4,FALSE),"") | G32: =IF($A32<>"",IF(ISBLANK(VLOOKUP($A32,tblProcesses2013!$A$3:$J$9998,8,FALSE)),"","?"),"") | H32: =IF(AND($G32<>"",$G32<>"?"),VLOOKUP($G32,tblProcessMultipliers2013!$A$3:$E$10000,3,FALSE),"") | I32: =IF($A32<>"",IF($H32<>"",$D32*$F32*$H32,$D32*$F32),0) -> 0
B33: =IF($A33<>"",VLOOKUP($A33,tblProcesses2013!$A$3:$J$9998,2,FALSE),"") | D33: =IF($A33<>"",VLOOKUP($A33,tblProcesses2013!$A$3:$J$9998,3,FALSE),"") | E33: =IF($A33<>"",VLOOKUP($A33,tblProcesses2013!$A$3:$J$9998,4,FALSE),"") | G33: =IF($A33<>"",IF(ISBLANK(VLOOKUP($A33,tblProcesses2013!$A$3:$J$9998,8,FALSE)),"","?"),"") | H33: =IF(AND($G33<>"",$G33<>"?"),VLOOKUP($G33,tblProcessMultipliers2013!$A$3:$E$10000,3,FALSE),"") | I33: =IF($A33<>"",IF($H33<>"",$D33*$F33*$H33,$D33*$F33),0) -> 0
B34: =IF($A34<>"",VLOOKUP($A34,tblProcesses2013!$A$3:$J$9998,2,FALSE),"") | D34: =IF($A34<>"",VLOOKUP($A34,tblProcesses2013!$A$3:$J$9998,3,FALSE),"") | E34: =IF($A34<>"",VLOOKUP($A34,tblProcesses2013!$A$3:$J$9998,4,FALSE),"") | G34: =IF($A34<>"",IF(ISBLANK(VLOOKUP($A34,tblProcesses2013!$A$3:$J$9998,8,FALSE)),"","?"),"") | H34: =IF(AND($G34<>"",$G34<>"?"),VLOOKUP($G34,tblProcessMultipliers2013!$A$3:$E$10000,3,FALSE),"") | I34: =IF($A34<>"",IF($H34<>"",$D34*$F34*$H34,$D34*$F34),0) -> 0
H35: Sub Total | I35: =SUM(I22:I34) -> 0
A37: Fasteners
A38: ID | B38: Fastener | C38: Use | D38: UnitCost | E38: Size1 | F38: Unit1 | G38: Size2 | H38: Unit2 | I38: Quantity | J38: Sub Total
B39: =IF($A39<>"",VLOOKUP($A39,tblFasteners2013!$A$4:$R$9999,2,FALSE),"") | D39: =IF($A39<>"",VLOOKUP($A39,tblFasteners2013!$A$4:$R$9999,11,FALSE),"") | F39: =IF($A39<>"",IF(VLOOKUP($A39,tblFasteners2013!$A$4:$R$9999,4,FALSE)<>FALSE,VLOOKUP($A39,tblFasteners2013!$A$4:$R$9999,4,FALSE),""),"") | H39: =IF($A39<>"",IF(VLOOKUP($A39,tblFasteners2013!$A$4:$R$9999,6,FALSE)<>FALSE,VLOOKUP($A39,tblFasteners2013!$A$4:$R$9999,6,FALSE),""),"") | J39: =IF($A39<>"",D39*I39,0) -> 0
B40: =IF($A40<>"",VLOOKUP($A40,tblFasteners2013!$A$4:$R$9999,2,FALSE),"") | D40: =IF($A40<>"",VLOOKUP($A40,tblFasteners2013!$A$4:$R$9999,11,FALSE),"") | F40: =IF($A40<>"",IF(VLOOKUP($A40,tblFasteners2013!$A$4:$R$9999,4,FALSE)<>FALSE,VLOOKUP($A40,tblFasteners2013!$A$4:$R$9999,4,FALSE),""),"") | H40: =IF($A40<>"",IF(VLOOKUP($A40,tblFasteners2013!$A$4:$R$9999,6,FALSE)<>FALSE,VLOOKUP($A40,tblFasteners2013!$A$4:$R$9999,6,FALSE),""),"") | J40: =IF($A40<>"",D40*I40,0) -> 0
B41: =IF($A41<>"",VLOOKUP($A41,tblFasteners2013!$A$4:$R$9999,2,FALSE),"") | D41: =IF($A41<>"",VLOOKUP($A41,tblFasteners2013!$A$4:$R$9999,11,FALSE),"") | F41: =IF($A41<>"",IF(VLOOKUP($A41,tblFasteners2013!$A$4:$R$9999,4,FALSE)<>FALSE,VLOOKUP($A41,tblFasteners2013!$A$4:$R$9999,4,FALSE),""),"") | H41: =IF($A41<>"",IF(VLOOKUP($A41,tblFasteners2013!$A$4:$R$9999,6,FALSE)<>FALSE,VLOOKUP($A41,tblFasteners2013!$A$4:$R$9999,6,FALSE),""),"") | J41: =IF($A41<>"",D41*I41,0) -> 0
B42: =IF($A42<>"",VLOOKUP($A42,tblFasteners2013!$A$4:$R$9999,2,FALSE),"") | D42: =IF($A42<>"",VLOOKUP($A42,tblFasteners2013!$A$4:$R$9999,11,FALSE),"") | F42: =IF($A42<>"",IF(VLOOKUP($A42,tblFasteners2013!$A$4:$R$9999,4,FALSE)<>FALSE,VLOOKUP($A42,tblFasteners2013!$A$4:$R$9999,4,FALSE),""),"") | H42: =IF($A42<>"",IF(VLOOKUP($A42,tblFasteners2013!$A$4:$R$9999,6,FALSE)<>FALSE,VLOOKUP($A42,tblFasteners2013!$A$4:$R$9999,6,FALSE),""),"") | J42: =IF($A42<>"",D42*I42,0) -> 0
B43: =IF($A43<>"",VLOOKUP($A43,tblFasteners2013!$A$4:$R$9999,2,FALSE),"") | D43: =IF($A43<>"",VLOOKUP($A43,tblFasteners2013!$A$4:$R$9999,11,FALSE),"") | F43: =IF($A43<>"",IF(VLOOKUP($A43,tblFasteners2013!$A$4:$R$9999,4,FALSE)<>FALSE,VLOOKUP($A43,tblFasteners2013!$A$4:$R$9999,4,FALSE),""),"") | H43: =IF($A43<>"",IF(VLOOKUP($A43,tblFasteners2013!$A$4:$R$9999,6,FALSE)<>FALSE,VLOOKUP($A43,tblFasteners2013!$A$4:$R$9999,6,FALSE),""),"") | J43: =IF($A43<>"",D43*I43,0) -> 0
B44: =IF($A44<>"",VLOOKUP($A44,tblFasteners2013!$A$4:$R$9999,2,FALSE),"") | D44: =IF($A44<>"",VLOOKUP($A44,tblFasteners2013!$A$4:$R$9999,11,FALSE),"") | F44: =IF($A44<>"",IF(VLOOKUP($A44,tblFasteners2013!$A$4:$R$9999,4,FALSE)<>FALSE,VLOOKUP($A44,tblFasteners2013!$A$4:$R$9999,4,FALSE),""),"") | H44: =IF($A44<>"",IF(VLOOKUP($A44,tblFasteners2013!$A$4:$R$9999,6,FALSE)<>FALSE,VLOOKUP($A44,tblFasteners2013!$A$4:$R$9999,6,FALSE),""),"") | J44: =IF($A44<>"",D44*I44,0) -> 0
B45: =IF($A45<>"",VLOOKUP($A45,tblFasteners2013!$A$4:$R$9999,2,FALSE),"") | D45: =IF($A45<>"",VLOOKUP($A45,tblFasteners2013!$A$4:$R$9999,11,FALSE),"") | F45: =IF($A45<>"",IF(VLOOKUP($A45,tblFasteners2013!$A$4:$R$9999,4,FALSE)<>FALSE,VLOOKUP($A45,tblFasteners2013!$A$4:$R$9999,4,FALSE),""),"") | H45: =IF($A45<>"",IF(VLOOKUP($A45,tblFasteners2013!$A$4:$R$9999,6,FALSE)<>FALSE,VLOOKUP($A45,tblFasteners2013!$A$4:$R$9999,6,FALSE),""),"") | J45: =IF($A45<>"",D45*I45,0) -> 0
B46: =IF($A46<>"",VLOOKUP($A46,tblFasteners2013!$A$4:$R$9999,2,FALSE),"") | D46: =IF($A46<>"",VLOOKUP($A46,tblFasteners2013!$A$4:$R$9999,11,FALSE),"") | F46: =IF($A46<>"",IF(VLOOKUP($A46,tblFasteners2013!$A$4:$R$9999,4,FALSE)<>FALSE,VLOOKUP($A46,tblFasteners2013!$A$4:$R$9999,4,FALSE),""),"") | H46: =IF($A46<>"",IF(VLOOKUP($A46,tblFasteners2013!$A$4:$R$9999,6,FALSE)<>FALSE,VLOOKUP($A46,tblFasteners2013!$A$4:$R$9999,6,FALSE),""),"") | J46: =IF($A46<>"",D46*I46,0) -> 0
I47: Sub Total | J47: =SUM(J39:J46) -> 0
A49: Tooling
A50: ID | B50: Tooling | C50: Use | D50: UnitCost | E50: Unit | F50: Quantity | G50: PVF | H50: FracIncld | I50: Sub Total
B51: =IF($A51<>"",VLOOKUP($A51,tblToolings2013!$A$3:$F$10000,3,FALSE),"") | D51: =IF($A51<>"",VLOOKUP($A51,tblToolings2013!$A$3:$F$10000,4,FALSE),"") | E51: =IF($A51<>"",VLOOKUP($A51,tblToolings2013!$A$3:$F$10000,5,FALSE),"") | G51: 3000 | I51: =IF($A51<>"",D51*F51/G51,0) -> 0
B52: =IF($A52<>"",VLOOKUP($A52,tblToolings2013!$A$3:$F$10000,3,FALSE),"") | D52: =IF($A52<>"",VLOOKUP($A52,tblToolings2013!$A$3:$F$10000,4,FALSE),"") | E52: =IF($A52<>"",VLOOKUP($A52,tblToolings2013!$A$3:$F$10000,5,FALSE),"") | G52: 3000 | I52: =IF($A52<>"",D52*F52/G52,0) -> 0
H53: Sub Total | I53: =SUM(I51:I52) -> 0

Sheet tblMaterials2013
A1: Materials Table. Posted Version 14.0, 25-Apr-2012 | J1: Added cost calculation
A2: Material ID | B2: Material | C2: Supplier | D2: Category | E2: Table Price | F2: Unit 1 | G2: Unit 2 | H2: C1 | I2: C2 | J2: Size1 | K2: Size2 | L2: Calc Value | M2: Modified | N2: Comments
A3: 1 | B3: Bearing Ball, Steel | C3: Any | D3: Bearings | E3: [C1]*[Size1]+[C2] | F3: mm | H3: 0.003 | I3: 0.05 | J3: 0 | L3: =H3*J3+I3 -> 0.05 | M3: 39938 | N3: [Size1]=Ball diameter (mm). Any steel materiAluminum This material is for a single steel sphere ball, not a complete bearing.
A4: 2 | B4: Bearing, Ball, Angular Contact | C4: Any | D4: Bearings | E4: [C1]*(([Size1]^2*[Size2]))^([C2]) | F4: mm | G4: mm | H4: 0.1 | I4: 0.5 | J4: 0 | K4: 0 | L4: =H4*((J4^2*K4))^(I4) -> 0 | M4: 39867 | N4: [Size1]=Outer diameter (mm), [Size2]=Thickness (mm). Not to be used for wheel bearings.
A5: 3 | B5: Bearing, Ball, Deep Groove | C5: Any | D5: Bearings | E5: [C1]*(([Size1]^2*[Size2]))^([C2]) | F5: mm | G5: mm | H5: 0.1 | I5: 0.5 | J5: 0 | K5: 0 | L5: =H5*((J5^2*K5))^(I5) -> 0 | M5: 39867 | N5: [Size1]=Outer diameter (mm), [Size2]=Thickness (mm). Not to be used for wheel bearings.
A6: 4 | B6: Bearing, Ball, Radial | C6: Any | D6: Bearings | E6: [C1]*(([Size1]^2*[Size2]))^([C2]) | F6: mm | G6: mm | H6: 0.1 | I6: 0.5 | J6: 0 | K6: 0 | L6: =H6*((J6^2*K6))^(I6) -> 0 | M6: 39867 | N6: [Size1]=Outer diameter (mm), [Size2]=Thickness (mm). Not to be used for wheel bearings.
A7: 5 | B7: Bearing, Cylindrical Roller | C7: Any | D7: Bearings | E7: [C1]*[Size1]*[Size2]+[C2] | F7: mm | G7: mm | H7: 0.0045 | I7: 3.6 | J7: 0 | K7: 0 | L7: =H7*J7*K7+I7 -> 3.6 | M7: 39867 | N7: [Size1]=Outer Diameter (mm). [Size2]=Length of bearing (mm). Not for wheel bearing use.
A8: 6 | B8: Bearing, Double Row, Ball, Angular Contact | C8: Any | D8: Bearings | E8: [C1]*(([Size1]^2*[Size2]))^([C2]) | F8: mm | G8: mm | H8: 0.1 | I8: 0.5 | J8: 0 | K8: 0 | L8: =H8*((J8^2*K8))^(I8) -> 0 | M8: 39867 | N8: [Size1]=Outer diameter (mm), [Size2]=Thickness (mm). Not to be used for wheel bearings.
A9: 7 | B9: Bearing, Double Row, Ball, Deep Groove | C9: Any | D9: Bearings | E9: [C1]*(([Size1]^2*[Size2]))^([C2]) | F9: mm | G9: mm | H9: 0.1 | I9: 0.5 | J9: 0 | K9: 0 | L9: =H9*((J9^2*K9))^(I9) -> 0 | M9: 39867 | N9: [Size1]=Outer diameter (mm), [Size2]=Thickness (mm). Not to be used for wheel bearings.
A10: 8 | B10: Bearing, Double Row, Ball, Radial | C10: Any | D10: Bearings | E10: [C1]*(([Size1]^2*[Size2]))^([C2]) | F10: mm | G10: mm | H10: 0.1 | I10: 0.5 | J10: 0 | K10: 0 | L10: =H10*((J10^2*K10))^(I10) -> 0 | M10: 39867 | N10: [Size1]=Outer diameter (mm), [Size2]=Thickness (mm). Not to be used for wheel bearings.
A11: 9 | B11: Bearing, Linear, Closed | C11: Any | D11: Bearings | E11: [C1]*[Size1]^2*[Size2]+[C2] | F11: mm | G11: mm | H11: 0.0001 | I11: 7.38 | J11: 0 | K11: 0 | L11: =H11*J11^2*K11+I11 -> 7.38 | M11: 39882 | N11: [Size1]=Outer diameter (mm), [Size2]=Length (mm). Use with end-supported shafts.
A12: 10 | B12: Bearing, Linear, Open | C12: Any | D12: Bearings | E12: [C1]*[Size1]^2*[Size2]+[C2] | F12: mm | G12: mm | H12: 0.00012 | I12: 13.1 | J12: 0 | K12: 0 | L12: =H12*J12^2*K12+I12 -> 13.1 | M12: 39882 | N12: [Size1]=Outer diameter (mm), [Size2]=Length (mm). Use with continuously supported shafts or where access to shaft ends is not possible.
A13: 11 | B13: Bearing, Needle | C13: Any | D13: Bearings | E13: [C1]*[Size1]*[Size2]+[C2] | F13: mm | G13: mm | H13: 0.0045 | I13: 3.6 | J13: 0 | K13: 0 | L13: =H13*J13*K13+I13 -> 3.6 | M13: 39867 | N13: [Size1]=Outer Diameter (mm). [Size2]=Length of bearing (mm). Any style of needle bearing. Not for wheel bearing use.
A14: 12 | B14: Bearing, Spherical | C14: Any | D14: Bearings | E14: [C1]*[Size1]^2+[C2] | F14: mm | H14: 0.03 | I14: 5 | J14: 0 | L14: =H14*J14^2+I14 -> 5 | N14: [Size1]=bore size (diameter of hole in spherical bearing).
A15: 13 | B15: Bearing, Tapered Needle | C15: Any | D15: Bearings | E15: [C1]*[Size1]*[Size2]+[C2] | F15: mm | G15: mm | H15: 0.0045 | I15: 10.45 | J15: 0 | K15: 0 | L15: =H15*J15*K15+I15 -> 10.45 | M15: 39867 | N15: [Size1]=Outer diameter (mm), [Size2]=Thickness (mm). Cost includes outer ring, inner ring and roller assembly. Not to be used for wheel bearings.
A16: 14 | B16: Bearing, Tapered Roller | C16: Any | D16: Bearings | E16: [C1]*[Size1]*[Size2]+[C2] | F16: mm | G16: mm | H16: 0.0045 | I16: 10.45 | J16: 0 | K16: 0 | L16: =H16*J16*K16+I16 -> 10.45 | M16: 39867 | N16: [Size1]=Outer diameter (mm), [Size2]=Thickness (mm). Cost includes outer ring, inner ring and roller assembly. Not to be used for wheel bearings.
A17: 15 | B17: Bearing, Thrust Needle Roller, Cage Assembly | C17: Any | D17: Bearings | E17: [C1]*[Size1]*[Size2]+[C2] | F17: mm | G17: mm | H17: 0.02 | I17: 0.15 | J17: 0 | K17: 0 | L17: =H17*J17*K17+I17 -> 0.15 | M17: 39867 | N17: [Size1]=Outer diameter (mm), [Size2]=Thickness (mm). Cost includes cage assembly but no washers. Not to be used for wheel bearings.
A18: 16 | B18: Bearing, Thrust Needle Roller, Washers | C18: Any | D18: Bearings | E18: [C1]*[Size1]^2*[Size2]+[C2] | F18: mm | G18: mm | H18: 0.0003 | I18: 0.13 | J18: 0 | K18: 0 | L18: =H18*J18^2*K18+I18 -> 0.13 | M18: 39867 | N18: [Size1]=Outer diameter (mm), [Size2]=Thickness (mm). For thrust bearings. Not to be used for wheel bearings.
A19: 17 | B19: Bushing, Student Built | C19: Student Built | D19: Bearings | E19: 0 | F19: unit | N19: Solid material (metal, plastic, etc.). No moving elements (ball, needle, etc.)
A20: 18 | B20: Rod End, Aluminum | C20: Any | D20: Bearings | E20: [C1]*[Size1]^2+[C2] | F20: mm | H20: 0.05 | I20: 3.8 | J20: 0 | L20: =H20*J20^2+I20 -> 3.8 | N20: [Size1]=bore size (diameter of hole in spherical bearing). Includes male/female and left/right threads.
A21: 19 | B21: Rod End, Industrial | C21: Any | D21: Bearings | E21: [C1]*[Size1]^2+[C2] | F21: mm | H21: 0.02 | I21: 1.216 | J21: 0 | L21: =H21*J21^2+I21 -> 1.216 | N21: [Size1]=bore size (diameter of hole in spherical bearing). Includes male/female and left/right threads.
A22: 20 | B22: Rod End, Precison (Aircraft) | C22: Any | D22: Bearings | E22: [C1]*[Size1]^2+[C2] | F22: mm | H22: 0.05 | I22: 5 | J22: 0 | L22: =H22*J22^2+I22 -> 5 | N22: [Size1]=bore size (diameter of hole in spherical bearing). Includes male/female and left/right threads.
A23: 21 | B23: Wheel Bearing, Ball, Angular Contact | C23: Any | D23: Bearings | E23: [C1]*(([Size1]^2*[Size2]))^([C2]) | F23: mm | G23: mm | H23: 0.4 | I23: 0.5 | J23: 0 | K23: 0 | L23: =H23*((J23^2*K23))^(I23) -> 0 | M23: 39867 | N23: [Size1]=Outer diameter (mm), [Size2]=Thickness (mm). Higher load capacity bearings intended for wheel/hub applications.
A24: 22 | B24: Wheel Bearing, Ball, Deep Groove | C24: Any | D24: Bearings | E24: [C1]*(([Size1]^2*[Size2]))^([C2]) | F24: mm | G24: mm | H24: 0.4 | I24: 0.5 | J24: 0 | K24: 0 | L24: =H24*((J24^2*K24))^(I24) -> 0 | M24: 39867 | N24: [Size1]=Outer diameter (mm), [Size2]=Thickness (mm). Higher load capacity bearings intended for wheel/hub applications.
A25: 23 | B25: Wheel Bearing, Ball, Radial | C25: Any | D25: Bearings | E25: [C1]*(([Size1]^2*[Size2]))^([C2]) | F25: mm | G25: mm | H25: 0.4 | I25: 0.5 | J25: 95 | K25: 20 | L25: =H25*((J25^2*K25))^(I25) -> 169.94117 | M25: 39867 | N25: [Size1]=Outer diameter (mm), [Size2]=Thickness (mm). Higher load capacity bearings intended for wheel/hub applications.
A26: 24 | B26: Wheel Bearing, Double Row, Ball, Angular Contact | C26: Any | D26: Bearings | E26: [C1]*(([Size1]^2*[Size2]))^([C2]) | F26: mm | G26: mm | H26: 0.4 | I26: 0.5 | J26: 0 | K26: 0 | L26: =H26*((J26^2*K26))^(I26) -> 0 | M26: 39867 | N26: [Size1]=Outer diameter (mm), [Size2]=Thickness (mm). Higher load capacity bearings intended for wheel/hub applications.
A27: 25 | B27: Wheel Bearing, Double Row, Ball, Deep Groove | C27: Any | D27: Bearings | E27: [C1]*(([Size1]^2*[Size2]))^([C2]) | F27: mm | G27: mm | H27: 0.4 | I27: 0.5 | J27: 0 | K27: 0 | L27: =H27*((J27^2*K27))^(I27) -> 0 | M27: 39867 | N27: [Size1]=Outer diameter (mm), [Size2]=Thickness (mm). Higher load capacity bearings intended for wheel/hub applications.
A28: 26 | B28: Wheel Bearing, Double Row, Ball, Radial | C28: Any | D28: Bearings | E28: [C1]*(([Size1]^2*[Size2]))^([C2]) | F28: mm | G28: mm | H28: 0.4 | I28: 0.5 | J28: 0 | K28: 0 | L28: =H28*((J28^2*K28))^(I28) -> 0 | M28: 39867 | N28: [Size1]=Outer diameter (mm), [Size2]=Thickness (mm). Higher load capacity bearings intended for wheel/hub applications.
A29: 27 | B29: Wheel Bearing, Tapered Needle | C29: Any | D29: Bearings | E29: [C1]*[Size1]*[Size2]+[C2] | F29: mm | G29: mm | H29: 0.009 | I29: 20.9 | J29: 0 | K29: 0 | L29: =H29*J29*K29+I29 -> 20.9 | M29: 39867 | N29: [Size1]=Outer diameter (mm), [Size2]=Thickness (mm). Higher load capacity bearings intended for wheel/hub applications.
A30: 28 | B30: Wheel Bearing, Tapered Roller | C30: Any | D30: Bearings | E30: [C1]*[Size1]*[Size2]+[C2] | F30: mm | G30: mm | H30: 0.009 | I30: 20.9 | J30: 0 | K30: 0 | L30: =H30*J30*K30+I30 -> 20.9 | M30: 39867 | N30: [Size1]=Outer diameter (mm), [Size2]=Thickness (mm). Higher load capacity bearings intended for wheel/hub applications.
A31: 29 | B31: 90-Degree Coupler, Tilton 72-560 | C31: Tilton | D31: Brake System | E31: 45 | F31: unit
A32: 30 | B32: 90-Degree Coupler, Tilton 72-561 | C32: Tilton | D32: Brake System | E32: 47.5 | F32: unit | M32: 39886
A33: 31 | B33: 90-Degree Coupler, Tilton 72-562 | C33: Tilton | D33: Brake System | E33: 50 | F33: unit | M33: 39886
A34: 32 | B34: ABS Kit, Bosch, M4 Kit 1 | C34: Bosch | D34: Brake System | E34: 3534 | F34: unit | M34: 40286
A35: 33 | B35: ABS Kit, Bosch, M4 Kit 2 | C35: Bosch | D35: Brake System | E35: 4158 | F35: unit | M35: 40286
A36: 34 | B36: Balance Bar, AP, CP5500-9 | C36: AP | D36: Brake System | E36: 270 | F36: unit
A37: 35 | B37: Balance Bar, AP, CP5520-4 | C37: AP | D37: Brake System | E37: 300 | F37: unit | M37: 39972
A38: 36 | B38: Balance Bar, Brake, Student Built | C38: Student Built | D38: Brake System | E38: 0 | F38: unit
A39: 37 | B39: Balance Bar, Sandtler, 128153 | C39: Sandtler | D39: Brake System | E39: 65 | F39: unit | M39: 40321
A40: 38 | B40: Balance Bar, Sandtler, 128154 | C40: Sandtler | D40: Brake System | E40: 73 | F40: unit | M40: 40321
A41: 39 | B41: Balance Bar, Timms Autoteile, 013 901 | C41: Timms Autoteile | D41: Brake System | E41: 28.4 | F41: unit | M41: 39936
A42: 40 | B42: Balance Bar, Tilton, 72-250 | C42: Tilton | D42: Brake System | E42: 30 | F42: unit
A43: 41 | B43: Balance Bar, Tilton, 72-260 | C43: Tilton | D43: Brake System | E43: 30 | F43: unit
A44: 42 | B44: Balance Bar, Tilton, 72-280 | C44: Tilton | D44: Brake System | E44: 312.5 | F44: unit
A45: 43 | B45: Balance Bar, Tilton, 72-281 | C45: Tilton | D45: Brake System | E45: 325 | F45: unit
A46: 44 | B46: Balance Bar, Tilton, 72-300 | C46: Any | D46: Brake System | E46: 32 | F46: unit | M46: 39887
A47: 45 | B47: Balance Bar Cable Adjuster, AP CP2905-8 | C47: AP | D47: Misc. | E47: 80 | M47: 39922
A48: 46 | B48: Balance Bar Cable Adjuster, Optimum Balance Prod | C48: Optimum Balance Products | D48: Misc. | E48: 22 | F48: unit | M48: 39925
A49: 47 | B49: Balance Bar Cable Adjuster, Right Angle Drive, AP CP5500-10 | C49: AP | D49: Brake System | E49: 103 | F49: unit | M49: 40286
A50: 48 | B50: Balance Bar Cable Adjuster, Sandtler, 128154 | C50: Sandtler | D50: Brake System | E50: 73 | F50: unit | M50: 40321
A51: 49 | B51: Brake Caliper Piston, Student Built | C51: Student Built | D51: Brake System | E51: 5 | F51: unit
A52: 50 | B52: Brake Caliper, AP, CP2577 | C52: AP | D52: Brake System | E52: 125 | F52: unit
A53: 51 | B53: Brake Caliper, AP, CP3696-6E0 | C53: AP | D53: Brake System | E53: 77.5 | F53: unit
A54: 52 | B54: Brake Caliper, AP, CP4226 | C54: AP | D54: Brake System | E54: 112.5 | F54: unit
A55: 53 | B55: Brake Caliper, AP, CP4227 | C55: AP | D55: Brake System | E55: 200 | F55: unit
A56: 54 | B56: Brake Caliper, AP, CP4488 | C56: AP | D56: Brake System | E56: 490 | F56: unit
A57: 55 | B57: Brake Caliper, AP, CP7003 | C57: AP | D57: Brake System | E57: 100 | F57: unit
A58: 56 | B58: Brake Caliper, AP, CP7853 | C58: AP | D58: Brake System | E58: 340.5 | F58: unit | M58: 40321
A59: 57 | B59: Brake Caliper, Beringer, 4H02 | C59: Beringer | D59: Brake System | E59: 110 | F59: unit | M59: 40670
A60: 58 | B60: Brake Caliper, Beringer, 4H12 | C60: Beringer | D60: Brake System | E60: 110 | F60: unit | M60: 40670
A61: 59 | B61: Brake Caliper, Beringer, 2D1 | C61: Beringer | D61: Brake System | E61: 83 | F61: unit | M61: 40670
A62: 60 | B62: Brake Caliper, Brembo, 20.5161.46/P32F | C62: Brembo | D62: Brake System | E62: 50 | F62: unit
A63: 61 | B63: Brake Caliper, Brembo, 20.6101/GP4-24 | C63: Brembo | D63: Brake System | E63: 450 | F63: unit
A64: 62 | B64: Brake Caliper, Brembo, 20.6950.10 | C64: Brembo | D64: Brake System | E64: 70 | F64: unit | M64: 39867
A65: 63 | B65: Brake Caliper, Brembo, 20.6950.11/P32G | C65: Brembo | D65: Brake System | E65: 70 | F65: unit | M65: 39909
A66: 64 | B66: Brake Caliper, Brembo, 20.6950.21/P32G | C66: Brembo | D66: Brake System | E66: 70 | F66: unit
A67: 65 | B67: Brake Caliper, Brembo, 20.6951.12/P34G | C67: Brembo | D67: Brake System | E67: 70 | F67: unit | M67: 39868
A68: 66 | B68: Brake Caliper, Brembo, 20.6951.50/P34C | C68: Brembo | D68: Brake System | E68: 70 | F68: unit
A69: 67 | B69: Brake Caliper, Harrison, 121019P | C69: Harrison | D69: Brake System | E69: 162 | F69: unit | M69: 39899
A70: 68 | B70: Brake Caliper, Harrison, 222004P | C70: Harrison | D70: Brake System | E70: 94 | F70: unit | M70: 39899
A71: 69 | B71: Brake Caliper, Harrison, 222005P | C71: Harrison | D71: Brake System | E71: 94 | F71: unit | M71: 39899
A72: 70 | B72: Brake Caliper, Honda, 45150-HP1-006 | C72: Honda/Nissin | D72: Brake System | E72: 55 | F72: unit
A73: 71 | B73: Brake Caliper, Honda, 45150-HN6-006 | C73: Honda/Nissin | D73: Brake System | E73: 30 | F73: unit
A74: 72 | B74: Brake Caliper, ISR, 22-028 | C74: ISR | D74: Brake System | E74: 65 | F74: unit
A75: 73 | B75: Brake Caliper, ISR, 22-034 | C75: ISR | D75: Brake System | E75: 240 | F75: unit | M75: 40288 | N75: Same cost left and right calipers
A76: 74 | B76: Brake Caliper, ISR, 22-036 | C76: ISR | D76: Brake System | E76: 77.5 | F76: unit | M76: 40257
A77: 75 | B77: Brake Caliper, ISR, 22-048 | C77: ISR | D77: Brake System | E77: 96 | F77: unit
A78: 76 | B78: Brake Caliper, ISR, 22-049 | C78: ISR | D78: Brake System | E78: 97 | F78: unit | M78: 40257
A79: 77 | B79: Brake Caliper, Magura, 908.1 | C79: Magura | D79: Brake System | E79: 226 | F79: unit | M79: 40257
A80: 78 | B80: Brake Caliper, Motorcycle, OEM (Any) | C80: Any | D80: Brake System | E80: AIR | F80: unit | M80: 39868
A81: 79 | B81: Brake Caliper, NISSIN, 08-1CP-32-15 | C81: Nissin | D81: Brake System | E81: 82 | F81: unit
A82: 80 | B82: Brake Caliper, NISSIN, 08-2CP-25-08 | C82: Nissin | D82: Brake System | E82: 96 | F82: unit
A83: 81 | B83: Brake Caliper, NISSIN, 08-2CT-25-06 | C83: Nissin | D83: Brake System | E83: 109 | F83: unit
A84: 82 | B84: Brake Caliper, NISSIN, 08-2CT-38-07 | C84: Nissin | D84: Brake System | E84: 109 | F84: unit
A85: 83 | B85: Brake Caliper, Polaris, 1910825/1910826 | C85: Polaris | D85: Brake System | E85: 66 | F85: unit | M85: 39873 | N85: Cost applies to either part number (similar part one left hand one right hand)
A86: 84 | B86: Brake Caliper, PVM, 6-piston Monoblock Radial Mount | C86: PVM | D86: Brake System | E86: 600 | F86: unit | M86: 39922
A87: 85 | B87: Brake Caliper, PVM, Front 4-Piston Monoblock Radial Mount | C87: PVM | D87: Brake System | E87: 385 | F87: unit | M87: 39922
A88: 86 | B88: Brake Caliper, PVM, Rear 4-Piston Monoblock Radial Mount | C88: PVM | D88: Brake System | E88: 225 | F88: unit | M88: 39922
A89: 87 | B89: Brake Caliper, PVM, 2-Piston Monoblock Radial Mount | C89: PVM | D89: Brake System | E89: 225 | F89: unit | M89: 39922
A90: 88 | B90: Brake Caliper, Spiegler, S070 | C90: Spiegler | D90: Brake System | E90: 207 | F90: unit | M90: 40321 | N90: Same price for left and righ calipers.
A91: 89 | B91: Brake Caliper, Spiegler, S108 | C91: Spiegler | D91: Brake System | E91: 257 | F91: unit | M91: 40321 | N91: Same price for left and righ calipers.
A92: 90 | B92: Brake Caliper, Student Built | C92: Student Built | D92: Brake System | E92: 0 | F92: unit
A93: 91 | B93: Brake Caliper, Tokico, 45150-MEL-023 | C93: Tokico | D93: Brake System | E93: 75 | F93: unit | M93: 39874
A94: 92 | B94: Brake Caliper, Wilwood, Billet Dynalite Single | C94: Wilwood | D94: Brake System | E94: 50 | F94: unit
A95: 93 | B95: Brake Caliper, Wilwood, Billet NDL | C95: Wilwood | D95: Brake System | E95: 78 | F95: unit
A96: 94 | B96: Brake Caliper, Wilwood, Dynalite Single Floater | C96: Wilwood | D96: Brake System | E96: 50 | F96: unit
A97: 95 | B97: Brake Caliper, Wilwood, DynaPro Radial | C97: Wilwood | D97: Brake System | E97: 110 | F97: unit
A98: 96 | B98: Brake Caliper, Wilwood, DynaPro Single | C98: Wilwood | D98: Brake System | E98: 53 | F98: unit | M98: 40286
A99: 97 | B99: Brake Caliper, Wilwood, Forged Dynalite | C99: Wilwood | D99: Brake System | E99: 68 | F99: unit
A100: 98 | B100: Brake Caliper, Wilwood, GP310 | C100: Wilwood | D100: Brake System | E100: 105 | F100: unit
...

Sheet tblProcesses2013
A1: Process Table. Posted Version 7, 30-Mar-2012
A2: Process ID | B2: Process | C2: Unit Cost | D2: Unit | E2: Category | F2: Tooling Required | G2: Near Net Shape | H2: Multiplier Type Used | I2: Modified | J2: Comments
A3: 2 | B3: Die Casting | C3: 4 | D3: kg | E3: Basic Forming | F3: Yes | G3: Yes
A4: 3 | B4: Investment Casting | C4: 8 | D4: kg | E4: Basic Forming | G4: Yes
A5: 4 | B5: Laser Powder Deposition | C5: 330 | D5: kg | E5: Basic Forming | G5: Yes
A6: 5 | B6: Plastic injection molding | C6: 2.75 | D6: kg | E6: Basic Forming | F6: Yes | G6: Yes
A7: 6 | B7: Powder Metal Forming | C7: 3 | D7: kg | E7: Basic Forming | F7: Yes | G7: Yes
A8: 7 | B8: Rapid Prototype - Stereo Lith. | C8: 32 | D8: kg | E8: Basic Forming | G8: Yes
A9: 8 | B9: Sand Casting | C9: 3 | D9: kg | E9: Basic Forming | F9: Yes
A10: 9 | B10: Exhaust System Ceramic Coating | C10: 25 | D10: m | E10: Coating | I10: 39868 | J10: Linear distance of coating on exhaust header and tubing including all runners, etc. Material included.
A11: 10 | B11: Cure, Autoclave | C11: 50 | D11: m^2 | E11: Composite | F11: Yes | J11: Includes all consumable materials and labor.
A12: 11 | B12: Cure, Oven | C12: 20 | D12: m^2 | E12: Composite | F12: Yes | J12: Includes all consumable materials and labor.
A13: 12 | B13: Cure, Room Temperature | C13: 10 | D13: m^2 | E13: Composite | F13: Yes | I13: 39868 | J13: Includes all consumable materials and labor.
A14: 13 | B14: Lamination, Fillament Winding | C14: 25 | D14: kg | E14: Composite | I14: 39898 | J14: Cost based on finished part mass of composite fibers and resin.
A15: 14 | B15: Lamination, Manual | C15: 35 | D15: m^2 | E15: Composite
A16: 15 | B16: Potting | C16: 0.5 | D16: cm | E16: Composite | I16: 39929 | J16: Cost based on perimeter of insert. Includes potting compund material cost
A17: 16 | B17: Resin application, Infusion Molding | C17: 2.5 | D17: m^2 | E17: Composite
A18: 17 | B18: Resin application, Manual | C18: 5 | D18: m^2 | E18: Composite | J18: If prepreg composites are used do not included the resin application step.
A19: 18 | B19: Attach Wire, Fork | C19: 0.25 | D19: unit | E19: Electrical - Attach Wires
A20: 19 | B20: Attach Wire, Quick connect terminal | C20: 0.10416667 | D20: unit | E20: Electrical - Attach Wires
A21: 20 | B21: Attach Wire, Ring | C21: 0.47916667 | D21: unit | E21: Electrical - Attach Wires
A22: 21 | B22: Attach Wire, Solder wire, bent | C22: 0.35416667 | D22: unit | E22: Electrical - Attach Wires
A23: 22 | B23: Attach Wire, Solder wire, not bent | C23: 0.52083333 | D23: unit | E23: Electrical - Attach Wires
A24: 23 | B24: Attach Wire, Terminated wire with screw | C24: 0.35416667 | D24: unit | E24: Electrical - Attach Wires
A25: 24 | B25: Attach Wire, Terminated wire with screw and nut | C25: 0.52083333 | D25: unit | E25: Electrical - Attach Wires
A26: 25 | B26: Attach Wire, Wire to screw | C26: 0.47916667 | D26: unit | E26: Electrical - Attach Wires
A27: 26 | B27: Attach Wire, Wire to screw with nut | C27: 0.64583333 | D27: unit | E27: Electrical - Attach Wires
A28: 27 | B28: Attach Wire, Wire to terminal block | C28: 0.35416667 | D28: unit | E28: Electrical - Attach Wires
A29: 28 | B29: Attach Wire, Wire wrap around terminal post | C29: 0.27083333 | D29: unit | E29: Electrical - Attach Wires
A30: 29 | B30: Install Tie Wrap (Zip Tie, Cable Clamp) | C30: 0.09375 | D30: unit | E30: Electrical - Bundle Install | I30: 39861
A31: 30 | B31: Wire Dressing (Install and route) | C31: 1 | D31: m | E31: Electrical - Bundle Install
A32: 31 | B32: Insert Bundle Into Tube or Sleeve | C32: 0.02 | D32: m | E32: Electrical - Bundle Processing | I32: 39837
A33: 32 | B33: Install Adhesive Cable Clamp | C33: 0.1875 | D33: unit | E33: Electrical - Bundle Processing
A34: 33 | B34: Lace | C34: 0.14583333 | D34: unit | E34: Electrical - Bundle Processing
A35: 34 | B35: Shrink Tube | C35: 0.15 | D35: cm | E35: Electrical - Bundle Processing | I35: 39898
A36: 35 | B36: Taping Wire Bundle | C36: 0.04 | D36: cm | E36: Electrical - Bundle Processing | I36: 39898
A37: 36 | B37: Connector Install, Circular, Bayonet | C37: 0.10833333 | D37: unit | E37: Electrical - Connections
A38: 37 | B38: Connector Install, Circular, Friction | C38: 0.13958333 | D38: unit | E38: Electrical - Connections
A39: 38 | B39: Connector Install, Circular, Screw Thread | C39: 0.23541667 | D39: unit | E39: Electrical - Connections
A40: 39 | B40: Connector Install, Square, Friction | C40: 0.13958333 | D40: unit | E40: Electrical - Connections
A41: 40 | B41: Connector Install, Square, Latch/Snap-on Type | C41: 0.16875 | D41: unit | E41: Electrical - Connections
A42: 41 | B42: Connector Install, Square, Screw (x2) | C42: 0.5 | D42: unit | E42: Electrical - Connections
A43: 42 | B43: Connector Install, Square, Spring Clip | C43: 0.20416667 | D43: unit | E43: Electrical - Connections
A44: 43 | B44: Lay Wire - Control | C44: 0.02 | D44: m | E44: Electrical - Layout | I44: 39838
A45: 44 | B45: Lay Wire - Power | C45: 0.03 | D45: m | E45: Electrical - Layout | I45: 39838
A46: 45 | B46: Lay Wire - Signal | C46: 0.02 | D46: m | E46: Electrical - Layout | I46: 39838
A47: 46 | B47: Crimp Wire | C47: 0.16666667 | D47: unit | E47: Electrical - Prep
A48: 47 | B48: Cut wire | C48: 0.083333333 | D48: unit | E48: Electrical - Prep
A49: 48 | B49: Strip Multi-Conductor | C49: 0.13 | D49: wire(s) | E49: Electrical - Prep | I49: 39837
A50: 49 | B50: Strip Wire | C50: 0.083333333 | D50: unit | E50: Electrical - Prep
A51: 50 | B51: Tin Wire | C51: 0.125 | D51: unit | E51: Electrical - Prep
A52: 51 | B52: Connector Assembley, Crimp | C52: 0.36 | D52: contacts | E52: Electrical - Wire in Connector | I52: 39837
A53: 52 | B53: Connector Assembley, Solder | C53: 0.24 | D53: contacts | E53: Electrical - Wire in Connector | I53: 39837
A54: 53 | B54: Hand - Start Only | C54: 0.12 | D54: unit | E54: Fasteners
A55: 54 | B55: Hand, Loose <= 25.4 mm | C55: 0.5 | D55: unit | E55: Fasteners
A56: 55 | B56: Hand, Loose <= 6.35 mm | C56: 0.25 | D56: unit | E56: Fasteners
A57: 56 | B57: Hand, Loose > 25.4 mm | C57: 0.75 | D57: unit | E57: Fasteners
A58: 57 | B58: Hand, Tight <= 6.35 mm | C58: 0.5 | D58: unit | E58: Fasteners
A59: 58 | B59: Power Tool <= 25.4 mm | C59: 0.25 | D59: unit | E59: Fasteners | H59: Fastener Installation
A60: 59 | B60: Power Tool <= 6.35 mm | C60: 0.25 | D60: unit | E60: Fasteners | H60: Fastener Installation
A61: 60 | B61: Power Tool > 25.4 mm | C61: 0.5 | D61: unit | E61: Fasteners | H61: Fastener Installation
A62: 61 | B62: Ratchet <= 25.4 mm | C62: 0.75 | D62: unit | E62: Fasteners | H62: Fastener Installation
A63: 62 | B63: Ratchet <= 6.35 mm | C63: 0.5 | D63: unit | E63: Fasteners | H63: Fastener Installation
A64: 63 | B64: Ratchet > 25.4 mm | C64: 1.5 | D64: unit | E64: Fasteners | H64: Fastener Installation
A65: 64 | B65: Reaction Tool <= 25.4 mm | C65: 0.25 | D65: unit | E65: Fasteners
A66: 65 | B66: Reaction Tool <= 6.35 mm | C66: 0.25 | D66: unit | E66: Fasteners
A67: 66 | B67: Reaction Tool > 25.4 mm | C67: 0.5 | D67: unit | E67: Fasteners
A68: 67 | B68: Screwdriver < 1 Turn | C68: 0.12 | D68: unit | E68: Fasteners | H68: Fastener Installation
A69: 68 | B69: Screwdriver > 1 Turn | C69: 0.5 | D69: unit | E69: Fasteners | H69: Fastener Installation
A70: 69 | B70: Wrench <= 25.4 mm | C70: 1.5 | D70: unit | E70: Fasteners | H70: Fastener Installation
A71: 70 | B71: Wrench <= 6.35 mm | C71: 1 | D71: unit | E71: Fasteners | H71: Fastener Installation
A72: 71 | B72: Wrench > 25.4 mm | C72: 2 | D72: unit | E72: Fasteners | H72: Fastener Installation
A73: 72 | B73: Braze | C73: 0.15 | D73: cm | E73: Joining | F73: Yes | I73: 39898
A74: 73 | B74: Sewing | C74: 0.08 | D74: cm | E74: Joining
A75: 74 | B75: Weld | C75: 0.15 | D75: cm | E75: Joining | F75: Yes | I75: 39868
A76: 75 | B76: Adjustment - Misc. | C76: 5 | D76: unit | E76: Labor | J76: Chain tension, etc.
A77: 76 | B77: Aerosol Apply | C77: 5.25 | D77: m^2 | E77: Labor
A78: 77 | B78: Annodize | C78: 0 | D78: unit | E78: Labor | I78: 39869 | J78: It is not necessary to include any cost for annodizing. Included for reference only.
A79: 78 | B79: Assemble, >20 kg, Interference | C79: 5.625 | D79: unit | E79: Labor | H79: Assembly
A80: 79 | B80: Assemble, >20 kg, Line-on-Line | C80: 3.75 | D80: unit | E80: Labor | H80: Assembly
A81: 80 | B81: Assemble, >20 kg, Loose | C81: 1.875 | D81: unit | E81: Labor | H81: Assembly
A82: 81 | B82: Assemble, 1 kg, Interference | C82: 0.1875 | D82: unit | E82: Labor | H82: Assembly
A83: 82 | B83: Assemble, 1 kg, Line-on-Line | C83: 0.125 | D83: unit | E83: Labor | H83: Assembly
A84: 83 | B84: Assemble, 1 kg, Loose | C84: 0.0625 | D84: unit | E84: Labor | H84: Assembly
A85: 84 | B85: Assemble, 10 kg, Interference | C85: 1.875 | D85: unit | E85: Labor | H85: Assembly
A86: 85 | B86: Assemble, 10 kg, Line-on-Line | C86: 1.25 | D86: unit | E86: Labor | H86: Assembly
A87: 86 | B87: Assemble, 10 kg, Loose | C87: 0.625 | D87: unit | E87: Labor | H87: Assembly
A88: 87 | B88: Assemble, 15 kg, Interference | C88: 2.8125 | D88: unit | E88: Labor | H88: Assembly
A89: 88 | B89: Assemble, 15 kg, Line-on-Line | C89: 1.875 | D89: unit | E89: Labor | H89: Assembly
A90: 89 | B90: Assemble, 15 kg, Loose | C90: 0.9375 | D90: unit | E90: Labor | H90: Assembly
... A99: 98 | B99: Assemble, 5 kg, Loose | C99: 0.3125 | D99: unit | E99: Labor | H99: Assembly
A100: 99 | B100: Brake Bleed - Per Bleeder Valve | C100: 2.5 | D100: unit | E100: Labor
A101: 100 | B101: Brush Apply | C101: 0.02 | D101: cm^2 | E101: Labor | J101: For use with glue, adhesives, paint, resin, etc.
A102: 101 | B102: Cut (scissors, knife) | C102: 0.06 | D102: cm | E102: Labor
A103: 102 | B103: Heat Treatment | C103: 0 | D103: unit | E103: Labor | I103: 39933 | J103: It is not necessary to include any cost for heat treatment. Included for reference only.
A104: 103 | B104: Liquid Applicator Gun | C104: 0.02 | D104: cm | E104: Labor | J104: For use with glue, adhesives, paint, resin, etc.
A105: 104 | B105: Liquid Apply - Pour Expanding Foam | C105: 2 | D105: m^3 | E105: Labor | J105: Cost based on volume of fully expanded final part before trimming
A106: 105 | B106: Liquid Apply - Spot | C106: 0.1 | D106: unit | E106: Labor | J106: For use with glue, adhesives, paint, resin, etc.
A107: 106 | B107: Machining Setup, Change | C107: 0.65 | D107: unit | E107: Labor | I107: 39873 | J107: The quantity for this process may be used to scale the cost to the number of parts yielded from each setup. For example if 4 parts can be machined from a single plate then the quantity per part may be set to 0.25 to spread the cost out over each part.
A108: 107 | B108: Machining Setup, Install and remove | C108: 1.3 | D108: unit | E108: Labor | I108: 39873 | J108: The quantity for this process may be used to scale the cost to the number of parts yielded from each setup. For example if 4 parts can be machined from a single plate then the quantity per part may be 0.25 to spread the cost out over each part.
...

Sheet tblProcessMultipliers2013
A1: Process Multipliers Table. Posted Version 1.3, 28-Nov-2010
A2: ProcessMultiplierID | B2: Process Multiplier | C2: Multiplier | D2: Use | E2: Comments
A3: 1 | B3: Assemble - Length > 0.5m | C3: 1.25 | D3: Assembly
A4: 2 | B4: Disassemble | C4: 0.8 | D4: Assembly | E4: To be used when removing parts or fasteners
A5: 3 | B5: Fastener Engagement Length > 2D | C5: 1.25 | D5: Fastener Installation
A6: 4 | B6: Fastener Engagement Length > 4D | C6: 1.5 | D6: Fastener Installation
A7: 5 | B7: Machine - Hole Length >= 4D | C7: 1.5 | D7: Drill, Tap
A8: 6 | B8: Machine - Hole Length >= 8D | C8: 3 | D8: Drill, Tap
A9: 7 | B9: Material - Composite | C9: 2 | D9: Machining
A10: 8 | B10: Material - Aluminum | C10: 1 | D10: Machining
A11: 9 | B11: Material - Brass | C11: 0.8 | D11: Machining
A12: 10 | B12: Material - Bronze | C12: 1.33 | D12: Machining
A13: 11 | B13: Material - Cast Iron | C13: 2.5 | D13: Machining
A14: 12 | B14: Material - Foam | C14: 0.33 | D14: Machining
A15: 13 | B15: Material - Inconel | C15: 4 | D15: Machining
A16: 14 | B16: Material - Magnesium | C16: 0.8 | D16: Machining
... A23: 21 | B23: Material - Wood (Hard or soft) | C23: 0.5 | D23: Machining
A24: 22 | B24: Repeat 2 | C24: 2 | E24: Optional, to show repetition of processes.
A25: 23 | B25: Repeat 3 | C25: 3 | E25: Optional, to show repetition of processes.
A26: 24 | B26: Repeat 4 | C26: 4 | E26: Optional, to show repetition of processes.
A27: 25 | B27: Repeat 5 | C27: 5 | E27: Optional, to show repetition of processes.
A28: 26 | B28: Repeat 6 | C28: 6 | E28: Optional, to show repetition of processes.
A29: 27 | B29: Repeat 7 | C29: 7 | E29: Optional, to show repetition of processes.
A30: 28 | B30: Repeat 8 | C30: 8 | E30: Optional, to show repetition of processes.
A31: 29 | B31: Repeat 9 | C31: 9 | E31: Optional, to show repetition of processes.
A32: 30 | B32: Repeat 10 | C32: 10 | E32: Optional, to show repetition of processes.

Sheet tblFasteners2013
A1: Version 3.2 | B1: Warning! Calc Price displays a value when Size 1 and Size 2 (if applicable) are entered. Make sure to read what Size1 and Size2 refer to in the comments field, fill out the appropriate size values before using calc price.
A2: 40670 | B2: Warning! Check Added/Modified Date to make sure you have the current costs. Some errors were found in the hose clamp equations in the calc price cell.
A3: Fastener ID | B3: Fastener | C3: Size 1 | D3: Unit 1 | E3: Size 2 | F3: Unit 2 | G3: Category | H3: Supplier | I3: c1 | J3: c2 | K3: Table Price | L3: System | M3: Category | N3: Calc Price | O3: Attachment | P3: DateAdded/Modified | Q3: Mass | R3: Comments
A4: 1 | B4: Steel Loop Straps, Rubber-Cushioned | C4: 25.4 | D4: mm | G4: Clamp | I4: 0.01 | J4: 0.01 | K4: [C1]*[Size1]+[C2] | M4: Clamp | N4: =I4*C4+J4 -> 0.264 | P4: 39855 | R4: [Size1]=final clamped diameter [mm]
A5: 2 | B5: Galvanized Steel Loop Straps | C5: 25.4 | D5: mm | G5: Clamp | I5: 0.002 | J5: 0.08 | K5: [C1]*[Size1]+[C2] | M5: Clamp | N5: =I5*C5+J5 -> 0.1308 | P5: 39855 | R5: [Size1]=final clamped diameter [mm]
A6: 3 | B6: Galvanized Steel Loop Straps, Rubber coated | C6: 25.4 | D6: mm | G6: Clamp | I6: 0.004 | J6: 0.08 | K6: [C1]*[Size1]+[C2] | M6: Clamp | N6: =I6*C6+J6 -> 0.1816 | P6: 39855 | R6: [Size1]=final clamped diameter [mm]
A7: 4 | B7: Hose Clamp, Spring Steel | C7: 25.4 | D7: mm | G7: Clamp | I7: 0.014 | J7: 0 | K7: [C1]*[Size1] | M7: Clamp | N7: =I7*C7+J7 -> 0.3556 | P7: 39855 | R7: [Size1]=final clamped diameter [mm]
A8: 5 | B8: Hose Clamp, Constant Tension | C8: 25.4 | D8: mm | G8: Clamp | I8: 0.123 | J8: 2.6 | K8: [C1]*[Size1]+[C2] | M8: Clamp | N8: =I8*C8+J8 -> 5.7242 | P8: 39855 | R8: [Size1]=final clamped diameter [mm]
A9: 6 | B9: Hose Clamp, Miniature Bolt | C9: 25.4 | D9: mm | I9: 0.004 | J9: 0.5 | K9: [C1]*[Size1]+[C2] | N9: =I9*C9+J9 -> 0.6016 | P9: 39867 | R9: [Size1]=final clamped diameter [mm]
A10: 7 | B10: Hose Clamp, Single Wire | C10: 6.35 | D10: mm | I10: 0.004 | J10: 0.02 | K10: [C1]*[Size1]+[C2] | N10: =I10*C10+J10 -> 0.0454 | P10: 39867 | R10: [Size1]=final clamped diameter [mm]
A11: 8 | B11: Hose Clamp, V-Band Quick Release | C11: 50 | D11: mm | I11: 0.118 | J11: 10.46 | K11: [C1]*[Size1]+[C2] | N11: =I11*C11+J11 -> 16.36 | P11: 39868 | R11: [Size1]=final clamped diameter [mm]
A12: 9 | B12: Hose Clamp, Worm Drive | C12: 25.4 | D12: mm | G12: Clamp | I12: 0.004 | J12: 0.5 | K12: [C1]*[Size1]+[C2] | M12: Clamp | N12: =I12*C12+J12 -> 0.6016 | P12: 39855 | R12: [Size1]=final clamped diameter [mm]
A13: 10 | B13: Retaining Ring, R-ring | C13: 6 | D13: mm | G13: Retaining Ring | I13: 0.00018 | J13: 0.013 | K13: [C1]*([Size1]^2)+[C2] | N13: =I13*(C13^2)+J13 -> 0.01948 | P13: 39855 | R13: [Size1]=shaft diameter [mm]
A14: 11 | B14: Retaining Ring, Internal | C14: 6 | D14: mm | G14: Retaining Ring | I14: 0.00018 | J14: 0.013 | K14: [C1]*([Size1]^2)+[C2] | N14: =I14*(C14^2)+J14 -> 0.01948 | P14: 39855 | R14: [Size1]=shaft diameter [mm]
A15: 12 | B15: Retaining Ring, External | C15: 6 | D15: mm | G15: Retaining Ring | I15: 0.00018 | J15: 0.013 | K15: [C1]*([Size1]^2)+[C2] | N15: =I15*(C15^2)+J15 -> 0.01948 | P15: 39855 | R15: [Size1]=shaft diameter [mm]
A16: 13 | B16: Retaining Ring, Spiral | C16: 6 | D16: mm | G16: Retaining Ring | I16: 0.00018 | J16: 0.025 | K16: [C1]*([Size1]^2)+[C2] | N16: =I16*(C16^2)+J16 -> 0.03148 | P16: 39855 | R16: [Size1]=shaft diameter [mm]
A17: 14 | B17: Alcoa Camloc Fastener 1/4 turn | C17: 4 | D17: unit | P17: 40670
A18: 15 | B18: Bolt, Aluminum | D18: mm | F18: mm | G18: Bolt | I18: 1 | J18: 0.005 | K18: [C1]/105154*[Size1]^2*[Size2]*SQRT([Size2])+([C2]*EXP(0.319*[Size1])) | N18: =I18/105154*C18^2*E18*SQRT(E18)+(J18*EXP(0.319*C18)) -> 0.005 | P18: 39868 | R18: [Size1]=diameter (mm). [Size2]=length (mm). Strength 255 Mpa. Special varities included (drilled head, locking, etc.).
A19: 16 | B19: Bolt, Banjo | D19: unit | P19: 39880 | R19: This item is in the materials table under plumbing
A20: 17 | B20: Bolt, Custom Design, Student Made | C20: 0 | D20: unit | G20: Bolt | P20: 39855 | R20: To be used for designs that do not match standard bolt configurations, such as threaded rocker arm posts
A21: 18 | B21: Bolt, Grade 10.9 (SAE 8) | C21: 12.7 | D21: mm | E21: 0 | F21: mm | G21: Bolt | I21: 1 | J21: 0.004 | K21: [C1]/105154*[Size1]^2*[Size2]*SQRT([Size2])+([C2]*EXP(0.319*[Size1])) | N21: =I21/105154*C21^2*E21*SQRT(E21)+(J21*EXP(0.319*C21)) -> 0.22988849 | R21: [Size1]=diameter (mm). [Size2]=length (mm). Strength 1030 Mpa. Special varities included (drilled head, locking, etc.).
A22: 19 | B22: Bolt, Grade 12.9 | C22: 12.7 | D22: mm | E22: 0 | F22: mm | G22: Bolt | I22: 1.25 | J22: 0.005 | K22: [C1]/105154*[Size1]^2*[Size2]*SQRT([Size2])+([C2]*EXP(0.319*[Size1])) | N22: =I22/105154*C22^2*E22*SQRT(E22)+(J22*EXP(0.319*C22)) -> 0.28736061 | R22: [Size1]=diameter (mm). [Size2]=length (mm). Strength 1170 Mpa. Special varities included (drilled head, locking, etc.).
A23: 20 | B23: Bolt, Grade 6.8 (SAE 3) and All Grades less than Metric 8.8 | C23: 12.7 | D23: mm | E23: 0 | F23: mm | G23: Bolt | I23: 0.6 | J23: 0.0024 | K23: [C1]/105154*[Size1]1^2*[Size1]2*SQRT([Size1]2)+([C2]*E[Size1]P(0.319*[Size1]1)) | N23: =I23/105154*C23^2*E23*SQRT(E23)+(J23*EXP(0.319*C23)) -> 0.13793309 | R23: [Size1]=diameter (mm). [Size2]=length (mm). Strength 670 Mpa. Special varities included (drilled head, locking, etc.)
A24: 21 | B24: Bolt, Grade 8.8 (SAE 5) | C24: 12.7 | D24: mm | E24: 0 | F24: mm | G24: Bolt | I24: 0.8 | J24: 0.003 | K24: [C1]/105154*[Size1]^2*[Size2]*SQRT([Size2])+([C2]*EXP(0.319*[Size1])) | N24: =I24/105154*C24^2*E24*SQRT(E24)+(J24*EXP(0.319*C24)) -> 0.17241637 | R24: [Size1]=diameter (mm). [Size2]=length (mm). Strength 830 Mpa. Special varities included (drilled head, locking, etc.).
A25: 22 | B25: Bolt, Grade AN | C25: 12.7 | D25: mm | E25: 0 | F25: mm | G25: Bolt | I25: 2 | J25: 0.02 | K25: [C1]/105154*[Size1]^2*[Size2]*SQRT([Size2])+([C2]*EXP(0.319*[Size1])) | N25: =I25/105154*C25^2*E25*SQRT(E25)+(J25*EXP(0.319*C25)) -> 1.1494424 | R25: [Size1]=diameter (mm). [Size2]=length (mm). Strength 830 Mpa. Special varities included (drilled head, locking, etc.).
A26: 23 | B26: Bolt, Grade NAS 12-Point | C26: 12.7 | D26: mm | E26: 0 | F26: mm | G26: Bolt | I26: 6.25 | J26: 0.1 | K26: [C1]/105154*[Size1]^2*[Size2]*SQRT([Size2])+([C2]*EXP(0.319*[Size1])) | N26: =I26/105154*C26^2*E26*SQRT(E26)+(J26*EXP(0.319*C26)) -> 5.7472122 | R26: [Size1]=diameter (mm). [Size2]=length (mm). Strength 1240 Mpa. Special varities included (drilled head, locking, etc.).
A27: 24 | B27: Bolt, Grade NAS 6-Point | C27: 12.7 | D27: mm | E27: 0 | F27: mm | G27: Bolt | I27: 2.5 | J27: 0.04 | K27: [C1]/105154*[Size1]^2*[Size2]*SQRT([Size2])+([C2]*EXP(0.319*[Size1])) | N27: =I27/105154*C27^2*E27*SQRT(E27)+(J27*EXP(0.319*C27)) -> 2.2988849 | R27: [Size1]=diameter (mm). [Size2]=length (mm). Strength 1100 Mpa. Special varities included (drilled head, locking, etc.).
A28: 25 | B28: Dzus Fastener, 1/4 Turn, Slotted Head | C28: 1.2 | D28: unit | P28: 39868 | R28: Includes 1/4 Turn stud, plate, spring and spring receptacle
A29: 26 | B29: Dzus Fastener, 1/4 Turn, Wing Head | C29: 1.3 | D29: unit | P29: 39868 | R29: Includes 1/4 Turn stud, plate, spring and spring receptacle
A30: 27 | B30: Eyebolt, Threaded, Steel | D30: mm | I30: 0.87 | J30: 0.05 | K30: [Quantity]*(([C1]*EXP([C2]*[Size1]))) | N30: =(I30*EXP(J30*C30)) -> 0.87 | P30: 39936 | R30: [Size1]=Inner Diameter of Eye
A31: 28 | B31: Hook and Loop, Hook Side (Velcro) | C31: 0.003 | D31: cm^2 | R31: Same cost for adhesive backed or non-adhesive backed. Only includes one side of joint (hook side)
A32: 29 | B32: Hook and Loop, Loop Side (Velcro) | C32: 0.002 | D32: cm^2 | R32: Same cost for adhesive backed or non-adhesive backed. Only includes one side of joint (loop side)
A33: 30 | B33: Nut, Custom Design, Student Made | C33: 0 | D33: unit | G33: Nut | P33: 39855 | R33: To be used for designs that do not match standard nut configurations, such as wheel nuts
A34: 31 | B34: Nut, Grade 10.9 (SAE 8) | D34: mm | F34: mm | G34: Nut | I34: 0.012 | J34: 0.2 | K34: ([C1]*EXP([C2]*[Size1])) | N34: =(I34*EXP(J34*C34)) -> 0.012 | P34: 39855 | R34: [Size1]=diameter (mm). Special varities included (drilled head, locking, etc.).
A35: 32 | B35: Nut, Grade 12.9 | D35: mm | F35: mm | G35: Nut | I35: 0.015 | J35: 0.2 | K35: ([C1]*EXP([C2]*[Size1])) | N35: =(I35*EXP(J35*C35)) -> 0.015 | P35: 39855 | R35: [Size1]=diameter (mm). Special varities included (drilled head, locking, etc.).
A36: 33 | B36: Nut, Grade 6.8 (SAE 3) and All Grades less than Metric 8.8 | D36: mm | F36: mm | G36: Nut | I36: 0.007 | J36: 0.2 | K36: ([C1]*EXP([C2]*[Size1])) | N36: =(I36*EXP(J36*C36)) -> 0.007 | P36: 39855
A37: 34 | B37: Nut, Grade 8.8 (SAE 5) | D37: mm | F37: mm | G37: Nut | I37: 0.009 | J37: 0.2 | K37: ([C1]*EXP([C2]*[Size1])) | N37: =(I37*EXP(J37*C37)) -> 0.009 | P37: 39855 | R37: [Size1]=diameter (mm). Special varities included (drilled head, locking, etc.).
A38: 35 | B38: Nut, Grade AN | D38: mm | F38: mm | G38: Nut | I38: 0.06 | J38: 0.2 | K38: ([C1]*EXP([C2]*[Size1])) | N38: =(I38*EXP(J38*C38)) -> 0.06 | P38: 39855 | R38: [Size1]=diameter (mm). Special varities included (drilled head, locking, etc.).
A39: 36 | B39: Nut, Grade NAS 12-Point | D39: mm | F39: mm | G39: Nut | I39: 0.3 | J39: 0.2 | K39: ([C1]*EXP([C2]*[Size1])) | N39: =(I39*EXP(J39*C39)) -> 0.3 | P39: 39855 | R39: [Size1]=diameter (mm). Special varities included (drilled head, locking, etc.).
A40: 37 | B40: Nut, Grade NAS 6-Point | D40: mm | F40: mm | G40: Nut | I40: 0.12 | J40: 0.2 | K40: ([C1]*EXP([C2]*[Size1])) | N40: =(I40*EXP(J40*C40)) -> 0.12 | P40: 39855 | R40: [Size1]=diameter (mm). Special varities included (drilled head, locking, etc.).
A41: 38 | B41: Nut, Lug | C41: 0.4 | D41: unit | P41: 39861 | R41: Any size
A42: 39 | B42: Nut, Panel Retained | D42: unit | F42: mm | I42: 0.05 | J42: 0.25 | K42: [Quantity]*([C1]*EXP([C2]*[Size1])) | N42: =(I42*EXP(J42*C42)) -> 0.05 | P42: 39873 | R42: Any type of nut with a retaining or anti-rotation feature for a panel (weldnut, etc.)
A43: 40 | B43: Nutsert (J-Nut) | D43: unit | F43: mm | I43: 0.05 | J43: 0.25 | K43: [C1]*EXP([C2]*[Size1]) | N43: =(I43*EXP(J43*C43)) -> 0.05 | P43: 39868
A44: 41 | B44: Pin, Cotter, Straight | C44: 0.05 | P44: 39880 | R44: All sizes up to 5mm diameter.
A45: 42 | B45: Pin, Cotter, Hairpin | C45: 0.08 | P45: 39880 | R45: All sizes up to 5mm wire diameter.
A46: 43 | B46: Pin, Plastic Push | C46: 0.1 | D46: unit | R46: Any size
A47: 44 | B47: Pin, Safety, Coiled Wire | D47: unit | F47: mm | I47: 0.009 | J47: 0.4 | K47: [Quantity]*([C1]*[Size1]+[C2]) | N47: =C47*I47+J47 -> 0.4 | P47: 39898 | R47: [Size1]=Usable length (mm).
A48: 45 | B48: Pin, Safety, Square Retainer Snap | D48: unit | F48: mm | I48: 0.001 | J48: 1 | K48: [Quantity]*([C1]*[Size1]*[Size2]+[C2]) | N48: =C48*E48*I48+J48 -> 1 | P48: 39898 | R48: [Size1]=Pin Diameter (mm), [Size2]=Usable length (mm).
A49: 46 | B49: Pin, Quick Release | D49: mm | F49: mm | I49: 0.001 | J49: 14 | K49: [Quantity]*([C1]*[Size1]^2*[Size2]+[C2]) | N49: =I49*C49^2*E49+J49 -> 14 | P49: 39880 | R49: [Size1]=Diameter (mm). [Size2]=Usable Length. Any style pin (T-handle, Ring Grip, etc.).
A50: 47 | B50: Rivet, Pop | C50: 0.03 | D50: unit | G50: Rivet | P50: 39855 | R50: Any diameter and length
A51: 48 | B51: Safety Wire | C51: 0 | D51: unit | P51: 39861 | R51: Included in labor cost.
A52: 49 | B52: Stud, Grade 10.9 (SAE 8) | D52: mm | F52: mm | G52: Stud | I52: 1 | J52: 0.004 | K52: [C1]/105154*[Size1]^2*[Size2]*SQRT([Size2])+([C2]*EXP(0.319*[Size1])) | N52: =I52/105154*C52^2*E52*SQRT(E52)+(J52*EXP(0.319*C52)) -> 0.004 | R52: [Size1]=diameter (mm). [Size2]=length (mm). Strength 1030 Mpa. Special varities included (drilled head, locking, etc.).
A53: 50 | B53: Stud, Grade 12.9 | D53: mm | F53: mm | G53: Stud | I53: 1.25 | J53: 0.005 | K53: [C1]/105154*[Size1]^2*[Size2]*SQRT([Size2])+([C2]*EXP(0.319*[Size1])) | N53: =I53/105154*C53^2*E53*SQRT(E53)+(J53*EXP(0.319*C53)) -> 0.005 | R53: [Size1]=diameter (mm). [Size2]=length (mm). Strength 1170 Mpa. Special varities included (drilled head, locking, etc.).
A54: 51 | B54: Stud, Grade 8.8 (SAE 5) | D54: mm | F54: mm | G54: Stud | I54: 0.8 | J54: 0.003 | K54: [C1]/105154*[Size1]^2*[Size2]*SQRT([Size2])+([C2]*EXP(0.319*[Size1])) | N54: =I54/105154*C54^2*E54*SQRT(E54)+(J54*EXP(0.319*C54)) -> 0.003 | R54: [Size1]=diameter (mm). [Size2]=length (mm). Strength 830 Mpa. Special varities included (drilled head, locking, etc.).
A55: 52 | B55: Tapered Pin, Threaded (AN386) | C55: 2.5 | D55: unit | P55: 39965 | R55: AN386 up to 6.35mm
A56: 53 | B56: Tie Wrap | C56: 0.04 | D56: unit | P56: 39861 | R56: Includes all styles and sizes of plastic cable ties including Cable Clamp, Zip Tie, etc.
A57: 54 | B57: Thread Insert | D57: mm | I57: 0.1 | K57: [Quantity]*([C1]*[Size1]) | P57: 39922 | R57: [Size1]=nominal hole diameter (mm).
A58: 55 | B58: Washer, Crush | D58: mm | P58: 39880 | R58: This item is in the materials table under plumbing
A59: 56 | B59: Washer, Grade 10.9 (SAE 8) | C59: 0.02 | D59: unit | G59: Washer | P59: 39855 | R59: [Size1]=diameter (mm). Any thickness. Special varities included (drilled head, locking, etc.).
A60: 57 | B60: Washer, Grade 12.9 | C60: 0.02 | D60: unit | G60: Washer | P60: 39855 | R60: [Size1]=diameter (mm). Any thickness. Special varities included (drilled head, locking, etc.).
A61: 58 | B61: Washer, Grade 6.8 (SAE 3) and All Grades less than Metric 8.8 | C61: 0.01 | D61: unit | G61: Washer | P61: 39855 | R61: [Size1]=diameter (mm). Any thickness. Special varities included (drilled head, locking, etc.).
A62: 59 | B62: Washer, Grade 8.8 (SAE 5) | C62: 0.01 | D62: unit | G62: Washer | P62: 39855 | R62: [Size1]=diameter (mm). Any thickness. Special varities included (drilled head, locking, etc.).
A63: 60 | B63: Washer, Grade AN | D63: mm | F63: mm | G63: Washer | I63: 0.005 | J63: 0.18 | K63: ([C1]*EXP([C2]*[Size1])) | N63: =(I63*EXP(J63*C63)) -> 0.005 | P63: 39855 | R63: [Size1]=diameter (mm). Any thickness. Special varities included (drilled head, locking, etc.).
A64: 61 | B64: Washer, Grade NAS 12-Point | D64: mm | F64: mm | G64: Washer | I64: 0.005 | J64: 0.36 | K64: ([C1]*EXP([C2]*[Size1])) | N64: =(I64*EXP(J64*C64)) -> 0.005 | P64: 39855
A65: 62 | B65: Washer, Grade NAS 6-Point | D65: mm | F65: mm | G65: Washer | I65: 0.005 | J65: 0.36 | K65: ([C1]*EXP([C2]*[Size1])) | N65: =(I65*EXP(J65*C65)) -> 0.005 | P65: 39855 | R65: [Size1]=diameter (mm). Any thickness. Special varities included (drilled head, locking, etc.).
M86: Fitting, AN
M87: Fitting, AN
M88: Fitting, AN
M89: Fitting, AN
M90: Fitting, AN
M91: Fitting, AN
M92: Fitting, AN
M93: Fitting, AN

Sheet tblToolings2013
A1: Tooling Table. Posted Version 1.4, 28-Nov-2010
A2: ID | B2: Process | C2: Tool | D2: Cost | E2: Unit | F2: Comments
A3: 1 | B3: All | C3: None | D3: 0
A4: 2 | B4: Die Casting | C4: Die Casting - Die | D4: 10000 | E4: die | F4: Per die not die set. Minimum number of dies is 2 per die set.
A5: 3 | B5: Lamination | C5: Lamination - Aluminum Tool | D5: 20000 | E5: m^2 | F5: Use surface area of tool that is used to form part geometry.
A6: 4 | B6: Lamination | C6: Lamination - Composite Tool | D6: 10000 | E6: m^2 | F6: Use surface area of tool that is used to form part geometry.
A7: 5 | B7: Lamination | C7: Lamination - Flat Panel Tool | D7: 1500 | E7: m^2 | F7: Use surface area of tool that is used to form part geometry. To use this tooling type composite part must have geometry that is possible to obtain from sheet metal tool with no complex curvature or shape. For example flat panel parts are allowed or parts with curvature in only one axis.
A8: 6 | B8: Lamination | C8: Lamination - Steel Tool | D8: 40000 | E8: m^2 | F8: Use surface area of tool that is used to form part geometry.
A9: 7 | B9: Plastic injection molding | C9: Plastic injection molding - Die | D9: 10000 | E9: die | F9: Per die not die set.
A10: 8 | B10: Powder Metal Forming | C10: Powder Metal Forming - Die | D10: 10000 | E10: die | F10: Per die not die set.
A11: 9 | B11: Sand Casting | C11: Sand Casting - Die | D11: 10000 | E11: die | F11: Per die not die set.
A12: 10 | B12: Sand Casting | C12: Sand Casting - Sand Core Package | D12: 5000 | E12: core | F12: Per core not core package.
A13: 11 | B13: Welds | C13: Welds - Welding Fixture | D13: 500 | E13: point | F13: Each point is a pickup or support point.
A14: 12 | B14: Braze | C14: Brazing Fixture | D14: 500 | E14: point | F14: Each point is a pickup or support point.

Sheet Cross Reference List
A1: Materials Cross Reference List Table. Commonly asked about items that do not appear in the table, or how to find them.
A2: Material ID | B2: Material | C2: Modified | D2: Cost As:
B3: Brake Fluid | C3: 39883 | D3: Fluid, Oil
B4: Differential Oil | C4: 39883 | D4: Fluid, Oil
B5: Radiator Filler Knecks | C5: 39883 | D5: Cost as made
B6: Radiator end caps | C6: 39883 | D6: Cost as made
B7: Electrical components (resistors, capacitors, etc.) | C7: 39883 | D7: Chassis Control Module (by function)
B8: Brake Hard Lines | C8: 39883 | D8: Cost from raw material (steel, aluminum, etc.) and include process operations to tubing ends
B9: Coolant Hose | C9: 39883 | D9: Cost from raw material (rubber, silicone, etc.)
B10: Radiator Hose | C10: 39883 | D10: Cost from raw material (rubber, silicone, etc.)

Sheet EV
A1: 1. Introduction
A2: The addition of the Electric vehicle category of cost components ugprdades the cost tables to now include fully parameterized costs for all components needed by electric vehicles. Thanks to the organizers of the Austrian and Australian competitions for the work that went into determining these costs.
A4: 2. Materials parameterization clarification
A6: 2.1. ECU, Rapid Prototyping
A7: This covers the dSpace microAutoBox and similar systems from ETAS and other suppliers. Those Units are differentiated by their deigned targets being Lab cars, HIL systems and prototype vehicles.
A9: 2.2. ECU, Automotive
A10: ECU designed for small- or large series application.
A12: 2.3. ECU, Industrial
A13: Industrial Automation – type Control units, e.g. Siemens SiMatic and similar systems from B&R and other suppliers. If you have a full system with e.g. Inverter and control modules, you will need to cost both separately (see 2.5.10)
A15: 2.4. ECU, EV, student built
A16: Use this item if you run your vehicle control (driver wish to motor torque request) on a self-designed unit, usually some kind of microcontroller + I/O. You will have to use the ECU add-ons (e.g. Traction Control) from the materials table if you have those features.
A18: 2.5. Chassis Control Modules
... A176: Chassis Control Module, + HV Precharge $50
